[
  {
    "word": "글로리아비스코뭉크치즈앤드차이브비스킷스틱"
  },
  {
    "word": "글로벌다큐멘터리기상천외동물커플"
  },
  {
    "word": "글로벌일자리프로젝트세계를보라"
  },
  {
    "word": "글을쓰자세상을바꾸는글을쓰자"
  },
  {
    "word": "글을쓸때언제나장편인건아니지"
  },
  {
    "word": "글로리아올레드약자편에선다"
  },
  {
    "word": "글로벌가족정착기한국에산다"
  },
  {
    "word": "글로벌바베큐페스티벌인홍성"
  },
  {
    "word": "글로벌콘텐츠페스티벌인순천"
  },
  {
    "word": "글로벌터치스페셜테이블타입"
  },
  {
    "word": "글로레이스판타스틱카니발"
  },
  {
    "word": "글로벌리퀘스트쇼어송포유"
  },
  {
    "word": "글로벌선진학교문경캠퍼스"
  },
  {
    "word": "글로벌주부퀴즈쇼징검다리"
  },
  {
    "word": "글로우업도전메이크업스타"
  },
  {
    "word": "글로컬문화인남산페스티벌"
  },
  {
    "word": "글라소비타민워터에너지"
  },
  {
    "word": "글라소비타민워터파워씨"
  },
  {
    "word": "글램메탈정예타우렌족장"
  },
  {
    "word": "글레이즈드불로장생도넛"
  },
  {
    "word": "글로벌라틴문화페스티벌"
  },
  {
    "word": "글로벌영도커피페스티벌"
  },
  {
    "word": "글로벌이노베이터페스타"
  },
  {
    "word": "글로벌퇴술랭퇴근후한끼"
  },
  {
    "word": "글로벌퇴슐랭퇴근후한끼"
  },
  {
    "word": "글로벌한국사그날세계는"
  },
  {
    "word": "글루민의아이스크림파티"
  },
  {
    "word": "글루타민산나트륨건조원"
  },
  {
    "word": "글루타민산나트륨사별원"
  },
  {
    "word": "글루타민산발효균배양원"
  },
  {
    "word": "글루타민산분리기조작원"
  },
  {
    "word": "글리세린다이아세테이트"
  },
  {
    "word": "글리치된현대자동차오라"
  },
  {
    "word": "글씨가지워진유리병편지"
  },
  {
    "word": "글자를알아볼수없는석판"
  },
  {
    "word": "글라이거의사탕엑스엘"
  },
  {
    "word": "글로리아패트리플러스"
  },
  {
    "word": "글로리윙하모니윙비트"
  },
  {
    "word": "글로벌아빠찾아삼만리"
  },
  {
    "word": "글로벌홈스테이집으로"
  },
  {
    "word": "글로우레슬링여인천하"
  },
  {
    "word": "글루타민가수분해효소"
  },
  {
    "word": "글리세린디아세테이트"
  },
  {
    "word": "글라이딩스트라이크"
  },
  {
    "word": "글락소스미스클라인"
  },
  {
    "word": "글래시에이트미사일"
  },
  {
    "word": "글로리오브가디언즈"
  },
  {
    "word": "글로리윙모탈윙비트"
  },
  {
    "word": "글로리의민들레씨앗"
  },
  {
    "word": "글로벌사이버대학교"
  },
  {
    "word": "글로벌정보쇼세계인"
  },
  {
    "word": "글로벌프로젝트나눔"
  },
  {
    "word": "글루스기수패치워크"
  },
  {
    "word": "글루코코르티코이드"
  },
  {
    "word": "글룸헤이븐사자의턱"
  },
  {
    "word": "글리세르알데하이드"
  },
  {
    "word": "글리치래리앤드로리"
  },
  {
    "word": "글리치팝오퍼레이터"
  },
  {
    "word": "글쓰기는한문장부터"
  },
  {
    "word": "글씨가흐릿해진노트"
  },
  {
    "word": "글씨가흐릿해진점괘"
  },
  {
    "word": "글자가나타나는난로"
  },
  {
    "word": "글라소비타민워터"
  },
  {
    "word": "글라시엘의얼음칼"
  },
  {
    "word": "글라이드블레이즈"
  },
  {
    "word": "글라트베크인질극"
  },
  {
    "word": "글레디에이터샌들"
  },
  {
    "word": "글레이셔국립공원"
  },
  {
    "word": "글렌로스골프클럽"
  },
  {
    "word": "글로리서클등장식"
  },
  {
    "word": "글로리어스넘버즈"
  },
  {
    "word": "글로리어스버스트"
  },
  {
    "word": "글로리오브빅토리"
  },
  {
    "word": "글로벌다큐멘터리"
  },
  {
    "word": "글로벌이슈투데이"
  },
  {
    "word": "글로비게리나연니"
  },
  {
    "word": "글루코프로테이드"
  },
  {
    "word": "글리벤클라마이드"
  },
  {
    "word": "글리세르알데히드"
  },
  {
    "word": "글리터응원메가폰"
  },
  {
    "word": "글린다크로우스킨"
  },
  {
    "word": "글씨가새겨진비석"
  },
  {
    "word": "글씨가흐릿한메모"
  },
  {
    "word": "글자를옮기는사람"
  },
  {
    "word": "글라스드아이즈"
  },
  {
    "word": "글라스마린쿠키"
  },
  {
    "word": "글라스비즈공예"
  },
  {
    "word": "글라스파이버폴"
  },
  {
    "word": "글라스하모니카"
  },
  {
    "word": "글라이거의이빨"
  },
  {
    "word": "글라이드부스터"
  },
  {
    "word": "글라햄의포스터"
  },
  {
    "word": "글래디얼체인지"
  },
  {
    "word": "글러트니플레어"
  },
  {
    "word": "글레이브던지기"
  },
  {
    "word": "글레이셜프리즌"
  },
  {
    "word": "글레이의포스터"
  },
  {
    "word": "글렌모어연대기"
  },
  {
    "word": "글로리아스콧호"
  },
  {
    "word": "글로리아올레드"
  },
  {
    "word": "글로리아패트리"
  },
  {
    "word": "글로리윙자벨린"
  },
  {
    "word": "글로벌선진학교"
  },
  {
    "word": "글로벌성공시대"
  },
  {
    "word": "글로벌텍스프리"
  },
  {
    "word": "글로소프테리스"
  },
  {
    "word": "글루민의포스터"
  },
  {
    "word": "글루코사민사막"
  },
  {
    "word": "글루코시다아제"
  },
  {
    "word": "글루코시데이스"
  },
  {
    "word": "글루코제네시스"
  },
  {
    "word": "글루탐산나트륨"
  },
  {
    "word": "글리신크레졸적"
  },
  {
    "word": "글리옥살라아제"
  },
  {
    "word": "글리옥살레이스"
  },
  {
    "word": "글리옥실산회로"
  },
  {
    "word": "글리치팝클래식"
  },
  {
    "word": "글리치팝프렌지"
  },
  {
    "word": "글리코겐축적증"
  },
  {
    "word": "글리코시다아제"
  },
  {
    "word": "글리코시데이스"
  },
  {
    "word": "글리클라자이드"
  },
  {
    "word": "글리터강령술사"
  },
  {
    "word": "글리터환상술사"
  },
  {
    "word": "글리투스커맨더"
  },
  {
    "word": "글과그림사이"
  },
  {
    "word": "글라디올러스"
  },
  {
    "word": "글라스노스트"
  },
  {
    "word": "글라스라이닝"
  },
  {
    "word": "글라스반도체"
  },
  {
    "word": "글라스스토리"
  },
  {
    "word": "글라신페이퍼"
  },
  {
    "word": "글라이더경기"
  },
  {
    "word": "글라이더왁스"
  },
  {
    "word": "글라이드록스"
  },
  {
    "word": "글라이드패스"
  },
  {
    "word": "글라햄의사진"
  },
  {
    "word": "글락스조각상"
  },
  {
    "word": "글란즈게이저"
  },
  {
    "word": "글래디얼리턴"
  },
  {
    "word": "글래디에이터"
  },
  {
    "word": "글레디에이터"
  },
  {
    "word": "글레이브투척"
  },
  {
    "word": "글레이셔배지"
  },
  {
    "word": "글레이셜슈즈"
  },
  {
    "word": "글레이셜체인"
  },
  {
    "word": "글레이의사진"
  },
  {
    "word": "글레이프니르"
  },
  {
    "word": "글로리레거시"
  },
  {
    "word": "글로리어스던"
  },
  {
    "word": "글로벌글로브"
  },
  {
    "word": "글로벌붕어빵"
  },
  {
    "word": "글로벌브랜드"
  },
  {
    "word": "글로벌추격전"
  },
  {
    "word": "글로벌코리안"
  },
  {
    "word": "글로벌퇴슐랭"
  },
  {
    "word": "글로비게리나"
  },
  {
    "word": "글로우스위치"
  },
  {
    "word": "글루그의꼬리"
  },
  {
    "word": "글루미선데이"
  },
  {
    "word": "글루민의사진"
  },
  {
    "word": "글루코사이드"
  },
  {
    "word": "글루코스생성"
  },
  {
    "word": "글루콘산발효"
  },
  {
    "word": "글루콘산소다"
  },
  {
    "word": "글루콜리피드"
  },
  {
    "word": "글루타싸이온"
  },
  {
    "word": "글루탐산발효"
  },
  {
    "word": "글루탐산소다"
  },
  {
    "word": "글루테티미드"
  },
  {
    "word": "글리세라이드"
  },
  {
    "word": "글리세롤발효"
  },
  {
    "word": "글리세롤연고"
  },
  {
    "word": "글리세린연고"
  },
  {
    "word": "글리신티올청"
  },
  {
    "word": "글리치솜브라"
  },
  {
    "word": "글리치팝단검"
  },
  {
    "word": "글리치팝도끼"
  },
  {
    "word": "글리치팝밴달"
  },
  {
    "word": "글리치팝불독"
  },
  {
    "word": "글리치팝오딘"
  },
  {
    "word": "글리치팝저지"
  },
  {
    "word": "글리치팝팬텀"
  },
  {
    "word": "글리코사이드"
  },
  {
    "word": "글리콜에테르"
  },
  {
    "word": "글리터근위병"
  },
  {
    "word": "글리터돌격병"
  },
  {
    "word": "글리터망치병"
  },
  {
    "word": "글리터방패병"
  },
  {
    "word": "글리터뱅가드"
  },
  {
    "word": "글리터수호병"
  },
  {
    "word": "글리터저격병"
  },
  {
    "word": "글리터종결자"
  },
  {
    "word": "글리터토벌대"
  },
  {
    "word": "글리프탈수지"
  },
  {
    "word": "글말언어행위"
  },
  {
    "word": "글벗초등학교"
  },
  {
    "word": "글썽글썽비석"
  },
  {
    "word": "글씨근육경련"
  },
  {
    "word": "글자디자이너"
  },
  {
    "word": "글자풀이노래"
  },
  {
    "word": "글게도드리"
  },
  {
    "word": "글곰뱅이쇠"
  },
  {
    "word": "글라골문자"
  },
  {
    "word": "글라스블록"
  },
  {
    "word": "글라우버염"
  },
  {
    "word": "글라주노프"
  },
  {
    "word": "글래드스턴"
  },
  {
    "word": "글래머러스"
  },
  {
    "word": "글래스러시"
  },
  {
    "word": "글래스로드"
  },
  {
    "word": "글래스호텔"
  },
  {
    "word": "글램모이라"
  },
  {
    "word": "글레어아이"
  },
  {
    "word": "글레이시아"
  },
  {
    "word": "글로리데이"
  },
  {
    "word": "글로리아벨"
  },
  {
    "word": "글로리오사"
  },
  {
    "word": "글로리홀법"
  },
  {
    "word": "글로방전등"
  },
  {
    "word": "글로벌리즘"
  },
  {
    "word": "글로벌예산"
  },
  {
    "word": "글로브극장"
  },
  {
    "word": "글로스타터"
  },
  {
    "word": "글로켄슈필"
  },
  {
    "word": "글로키디움"
  },
  {
    "word": "글로플러그"
  },
  {
    "word": "글록시니아"
  },
  {
    "word": "글루코사민"
  },
  {
    "word": "글루코시드"
  },
  {
    "word": "글루코오스"
  },
  {
    "word": "글루콘산균"
  },
  {
    "word": "글루쿠론산"
  },
  {
    "word": "글루타르산"
  },
  {
    "word": "글루타티온"
  },
  {
    "word": "글리세리드"
  },
  {
    "word": "글리세린산"
  },
  {
    "word": "글리세린욕"
  },
  {
    "word": "글리시리진"
  },
  {
    "word": "글리오톡신"
  },
  {
    "word": "글리옥살린"
  },
  {
    "word": "글리옥살산"
  },
  {
    "word": "글리옥시솜"
  },
  {
    "word": "글리옥실산"
  },
  {
    "word": "글리온선언"
  },
  {
    "word": "글리치레미"
  },
  {
    "word": "글리코시드"
  },
  {
    "word": "글리터궁병"
  },
  {
    "word": "글리터창병"
  },
  {
    "word": "글림계전관"
  },
  {
    "word": "글방도련님"
  },
  {
    "word": "글방서방님"
  },
  {
    "word": "글벗중학교"
  },
  {
    "word": "글쎄올시다"
  },
  {
    "word": "글이쓰인책"
  },
  {
    "word": "글줄채자기"
  },
  {
    "word": "글겅글겅"
  },
  {
    "word": "글겅이질"
  },
  {
    "word": "글게양청"
  },
  {
    "word": "글겡이질"
  },
  {
    "word": "글깃글깃"
  },
  {
    "word": "글다듬기"
  },
  {
    "word": "글라디오"
  },
  {
    "word": "글라레스"
  },
  {
    "word": "글라스립"
  },
  {
    "word": "글라스자"
  },
  {
    "word": "글라시엘"
  },
  {
    "word": "글라우버"
  },
  {
    "word": "글라우신"
  },
  {
    "word": "글라이거"
  },
  {
    "word": "글라이더"
  },
  {
    "word": "글라이드"
  },
  {
    "word": "글라이딩"
  },
  {
    "word": "글라이신"
  },
  {
    "word": "글라이온"
  },
  {
    "word": "글라티온"
  },
  {
    "word": "글랏코프"
  },
  {
    "word": "글래머주"
  },
  {
    "word": "글래스고"
  },
  {
    "word": "글래스펠"
  },
  {
    "word": "글램걸스"
  },
  {
    "word": "글램패션"
  },
  {
    "word": "글러버산"
  },
  {
    "word": "글러버탑"
  },
  {
    "word": "글레이브"
  },
  {
    "word": "글레이즈"
  },
  {
    "word": "글레이징"
  },
  {
    "word": "글레이층"
  },
  {
    "word": "글렌개리"
  },
  {
    "word": "글렌굴드"
  },
  {
    "word": "글렌첸트"
  },
  {
    "word": "글로램프"
  },
  {
    "word": "글로리아"
  },
  {
    "word": "글로리홀"
  },
  {
    "word": "글로방전"
  },
  {
    "word": "글로불린"
  },
  {
    "word": "글로스터"
  },
  {
    "word": "글로우업"
  },
  {
    "word": "글로전압"
  },
  {
    "word": "글롬마강"
  },
  {
    "word": "글루시톨"
  },
  {
    "word": "글루카곤"
  },
  {
    "word": "글루코스"
  },
  {
    "word": "글루콘산"
  },
  {
    "word": "글루타민"
  },
  {
    "word": "글루탐산"
  },
  {
    "word": "글루테닌"
  },
  {
    "word": "글루텔린"
  },
  {
    "word": "글리비체"
  },
  {
    "word": "글리사드"
  },
  {
    "word": "글리산도"
  },
  {
    "word": "글리세롤"
  },
  {
    "word": "글리세린"
  },
  {
    "word": "글리아딘"
  },
  {
    "word": "글리옥살"
  },
  {
    "word": "글리코겐"
  },
  {
    "word": "글리코젠"
  },
  {
    "word": "글리콜산"
  },
  {
    "word": "글리클럽"
  },
  {
    "word": "글방물림"
  },
  {
    "word": "글방사랑"
  },
  {
    "word": "글방퇴물"
  },
  {
    "word": "글벙어리"
  },
  {
    "word": "글심부름"
  },
  {
    "word": "글썽글썽"
  },
  {
    "word": "글씨연축"
  },
  {
    "word": "글자개혁"
  },
  {
    "word": "글자도안"
  },
  {
    "word": "글자모임"
  },
  {
    "word": "글자모자"
  },
  {
    "word": "글자무늬"
  },
  {
    "word": "글자밀도"
  },
  {
    "word": "글자악보"
  },
  {
    "word": "글자인식"
  },
  {
    "word": "글자전쟁"
  },
  {
    "word": "글자조각"
  },
  {
    "word": "글자종이"
  },
  {
    "word": "글자충전"
  },
  {
    "word": "글자크기"
  },
  {
    "word": "글자풀이"
  },
  {
    "word": "글줄주기"
  },
  {
    "word": "글줄채자"
  },
  {
    "word": "글컹글컹"
  },
  {
    "word": "글품쟁이"
  },
  {
    "word": "글가락"
  },
  {
    "word": "글거리"
  },
  {
    "word": "글거지"
  },
  {
    "word": "글겅이"
  },
  {
    "word": "글겡이"
  },
  {
    "word": "글공부"
  },
  {
    "word": "글구멍"
  },
  {
    "word": "글그램"
  },
  {
    "word": "글깅이"
  },
  {
    "word": "글꼬리"
  },
  {
    "word": "글닐기"
  },
  {
    "word": "글동냥"
  },
  {
    "word": "글동무"
  },
  {
    "word": "글동접"
  },
  {
    "word": "글뒤주"
  },
  {
    "word": "글라디"
  },
  {
    "word": "글라세"
  },
  {
    "word": "글라스"
  },
  {
    "word": "글라임"
  },
  {
    "word": "글라햄"
  },
  {
    "word": "글래머"
  },
  {
    "word": "글래스"
  },
  {
    "word": "글래시"
  },
  {
    "word": "글램록"
  },
  {
    "word": "글램핑"
  },
  {
    "word": "글러로"
  },
  {
    "word": "글러브"
  },
  {
    "word": "글레어"
  },
  {
    "word": "글레이"
  },
  {
    "word": "글렝이"
  },
  {
    "word": "글로디"
  },
  {
    "word": "글로리"
  },
  {
    "word": "글로본"
  },
  {
    "word": "글로브"
  },
  {
    "word": "글로빈"
  },
  {
    "word": "글로시"
  },
  {
    "word": "글로우"
  },
  {
    "word": "글루민"
  },
  {
    "word": "글루스"
  },
  {
    "word": "글루온"
  },
  {
    "word": "글루크"
  },
  {
    "word": "글루텐"
  },
  {
    "word": "글리마"
  },
  {
    "word": "글리버"
  },
  {
    "word": "글리세"
  },
  {
    "word": "글리신"
  },
  {
    "word": "글리치"
  },
  {
    "word": "글리콘"
  },
  {
    "word": "글리콜"
  },
  {
    "word": "글리터"
  },
  {
    "word": "글린카"
  },
  {
    "word": "글립패"
  },
  {
    "word": "글마디"
  },
  {
    "word": "글마루"
  },
  {
    "word": "글말글"
  },
  {
    "word": "글말체"
  },
  {
    "word": "글맵시"
  },
  {
    "word": "글머리"
  },
  {
    "word": "글밑천"
  },
  {
    "word": "글바보"
  },
  {
    "word": "글솜씨"
  },
  {
    "word": "글스기"
  },
  {
    "word": "글쎄다"
  },
  {
    "word": "글쎄요"
  },
  {
    "word": "글쓰기"
  },
  {
    "word": "글쓴이"
  },
  {
    "word": "글씨름"
  },
  {
    "word": "글씨본"
  },
  {
    "word": "글씨체"
  },
  {
    "word": "글안장"
  },
  {
    "word": "글월문"
  },
  {
    "word": "글자갈"
  },
  {
    "word": "글자꼴"
  },
  {
    "word": "글자렬"
  },
  {
    "word": "글자론"
  },
  {
    "word": "글자막"
  },
  {
    "word": "글자본"
  },
  {
    "word": "글자수"
  },
  {
    "word": "글자체"
  },
  {
    "word": "글자판"
  },
  {
    "word": "글자학"
  },
  {
    "word": "글장님"
  },
  {
    "word": "글장이"
  },
  {
    "word": "글재간"
  },
  {
    "word": "글재주"
  },
  {
    "word": "글쟁이"
  },
  {
    "word": "글짓기"
  },
  {
    "word": "글쪼각"
  },
  {
    "word": "글쪽지"
  },
  {
    "word": "글치레"
  },
  {
    "word": "글치장"
  },
  {
    "word": "글테기"
  },
  {
    "word": "글토막"
  },
  {
    "word": "글희영"
  },
  {
    "word": "글감"
  },
  {
    "word": "글강"
  },
  {
    "word": "글겅"
  },
  {
    "word": "글게"
  },
  {
    "word": "글구"
  },
  {
    "word": "글귀"
  },
  {
    "word": "글깃"
  },
  {
    "word": "글꼴"
  },
  {
    "word": "글눈"
  },
  {
    "word": "글니"
  },
  {
    "word": "글다"
  },
  {
    "word": "글단"
  },
  {
    "word": "글덕"
  },
  {
    "word": "글뎨"
  },
  {
    "word": "글때"
  },
  {
    "word": "글럭"
  },
  {
    "word": "글로"
  },
  {
    "word": "글리"
  },
  {
    "word": "글말"
  },
  {
    "word": "글맛"
  },
  {
    "word": "글먼"
  },
  {
    "word": "글메"
  },
  {
    "word": "글발"
  },
  {
    "word": "글방"
  },
  {
    "word": "글밭"
  },
  {
    "word": "글벗"
  },
  {
    "word": "글보"
  },
  {
    "word": "글속"
  },
  {
    "word": "글쇠"
  },
  {
    "word": "글시"
  },
  {
    "word": "글썽"
  },
  {
    "word": "글쎄"
  },
  {
    "word": "글씨"
  },
  {
    "word": "글안"
  },
  {
    "word": "글영"
  },
  {
    "word": "글월"
  },
  {
    "word": "글위"
  },
  {
    "word": "글음"
  },
  {
    "word": "글자"
  },
  {
    "word": "글장"
  },
  {
    "word": "글점"
  },
  {
    "word": "글제"
  },
  {
    "word": "글조"
  },
  {
    "word": "글줄"
  },
  {
    "word": "글지"
  },
  {
    "word": "글채"
  },
  {
    "word": "글첩"
  },
  {
    "word": "글체"
  },
  {
    "word": "글초"
  },
  {
    "word": "글컹"
  },
  {
    "word": "글콩"
  },
  {
    "word": "글탄"
  },
  {
    "word": "글투"
  },
  {
    "word": "글페"
  },
  {
    "word": "글편"
  },
  {
    "word": "글푸"
  },
  {
    "word": "글품"
  },
  {
    "word": "글피"
  },
  {
    "word": "글획"
  },
  {
    "word": "글"
  }
]