[
  {
    "word": "늦기전에어학연수샬라샬라"
  },
  {
    "word": "늦은밤너의집앞골목길에서"
  },
  {
    "word": "늦은밤헤어지긴너무아쉬워"
  },
  {
    "word": "늦기전에엄마와여행하기"
  },
  {
    "word": "늦가을무민골짜기"
  },
  {
    "word": "늦어도11월에는"
  },
  {
    "word": "늦둥이이른둥이"
  },
  {
    "word": "늦은중모리장단"
  },
  {
    "word": "늦게핀모험가"
  },
  {
    "word": "늦고추잠자리"
  },
  {
    "word": "늦벌레밤나비"
  },
  {
    "word": "늦은강강술래"
  },
  {
    "word": "늦게온소포"
  },
  {
    "word": "늦게피는꽃"
  },
  {
    "word": "늦고사리삼"
  },
  {
    "word": "늦바람둥이"
  },
  {
    "word": "늦은중모리"
  },
  {
    "word": "늦잠꾸러기"
  },
  {
    "word": "늦하늬바람"
  },
  {
    "word": "늦하니바름"
  },
  {
    "word": "늦갈새끼"
  },
  {
    "word": "늦강냉이"
  },
  {
    "word": "늦고구마"
  },
  {
    "word": "늦마바람"
  },
  {
    "word": "늦모내기"
  },
  {
    "word": "늦밭갈이"
  },
  {
    "word": "늦배새끼"
  },
  {
    "word": "늦복숭아"
  },
  {
    "word": "늦부지런"
  },
  {
    "word": "늦서리해"
  },
  {
    "word": "늦어지기"
  },
  {
    "word": "늦었음을"
  },
  {
    "word": "늦은가락"
  },
  {
    "word": "늦은배웅"
  },
  {
    "word": "늦은사랑"
  },
  {
    "word": "늦은삼절"
  },
  {
    "word": "늦은한잎"
  },
  {
    "word": "늦은후회"
  },
  {
    "word": "늦잠쟁이"
  },
  {
    "word": "늦춘화음"
  },
  {
    "word": "늦춤선로"
  },
  {
    "word": "늦피마주"
  },
  {
    "word": "늦가을"
  },
  {
    "word": "늦갈이"
  },
  {
    "word": "늦감자"
  },
  {
    "word": "늦거름"
  },
  {
    "word": "늦거리"
  },
  {
    "word": "늦걸굼"
  },
  {
    "word": "늦겨울"
  },
  {
    "word": "늦곡식"
  },
  {
    "word": "늦공부"
  },
  {
    "word": "늦과실"
  },
  {
    "word": "늦과일"
  },
  {
    "word": "늦김치"
  },
  {
    "word": "늦깎이"
  },
  {
    "word": "늦당콩"
  },
  {
    "word": "늦더위"
  },
  {
    "word": "늦동이"
  },
  {
    "word": "늦동지"
  },
  {
    "word": "늦둥이"
  },
  {
    "word": "늦맺이"
  },
  {
    "word": "늦바람"
  },
  {
    "word": "늦바름"
  },
  {
    "word": "늦버섯"
  },
  {
    "word": "늦벌레"
  },
  {
    "word": "늦벼모"
  },
  {
    "word": "늦보리"
  },
  {
    "word": "늦비료"
  },
  {
    "word": "늦사과"
  },
  {
    "word": "늦사리"
  },
  {
    "word": "늦새끼"
  },
  {
    "word": "늦새우"
  },
  {
    "word": "늦서리"
  },
  {
    "word": "늦시집"
  },
  {
    "word": "늦심기"
  },
  {
    "word": "늦싸리"
  },
  {
    "word": "늦아침"
  },
  {
    "word": "늦여름"
  },
  {
    "word": "늦은불"
  },
  {
    "word": "늦은씨"
  },
  {
    "word": "늦자식"
  },
  {
    "word": "늦작물"
  },
  {
    "word": "늦장가"
  },
  {
    "word": "늦장마"
  },
  {
    "word": "늦재주"
  },
  {
    "word": "늦저녁"
  },
  {
    "word": "늦점심"
  },
  {
    "word": "늦추위"
  },
  {
    "word": "늦춘음"
  },
  {
    "word": "늦춤히"
  },
  {
    "word": "늦품종"
  },
  {
    "word": "늦하늬"
  },
  {
    "word": "늦호박"
  },
  {
    "word": "늦휴가"
  },
  {
    "word": "늦가"
  },
  {
    "word": "늦꽃"
  },
  {
    "word": "늦다"
  },
  {
    "word": "늦달"
  },
  {
    "word": "늦닭"
  },
  {
    "word": "늦마"
  },
  {
    "word": "늦모"
  },
  {
    "word": "늦물"
  },
  {
    "word": "늦밤"
  },
  {
    "word": "늦배"
  },
  {
    "word": "늦번"
  },
  {
    "word": "늦벼"
  },
  {
    "word": "늦복"
  },
  {
    "word": "늦봄"
  },
  {
    "word": "늦뽕"
  },
  {
    "word": "늦잎"
  },
  {
    "word": "늦잠"
  },
  {
    "word": "늦장"
  },
  {
    "word": "늦종"
  },
  {
    "word": "늦줄"
  },
  {
    "word": "늦철"
  },
  {
    "word": "늦체"
  },
  {
    "word": "늦추"
  },
  {
    "word": "늦춤"
  },
  {
    "word": "늦콩"
  },
  {
    "word": "늦팥"
  },
  {
    "word": "늦풀"
  },
  {
    "word": "늦피"
  },
  {
    "word": "늦"
  }
]