[
  {
    "word": "빅토리아위너오스트웬왕비는세상에서제일거만하다"
  },
  {
    "word": "빅토리무도회사건애거서크리스티전집"
  },
  {
    "word": "빅코미디크로스오버시트콤스페셜"
  },
  {
    "word": "빅샤크580일간의해저일주"
  },
  {
    "word": "빅시티어드벤처샌프란시스코"
  },
  {
    "word": "빅샤크3젤리몬스터대소동"
  },
  {
    "word": "빅토리아로즈연파랑페인트"
  },
  {
    "word": "빅트립아기팬더배달대모험"
  },
  {
    "word": "빅풋주니어2패밀리가떴다"
  },
  {
    "word": "빅플로앤올리힙합에미치다"
  },
  {
    "word": "빅데이터아키텍처전문가"
  },
  {
    "word": "빅베이프쥴의성공과몰락"
  },
  {
    "word": "빅브라더페도라설계도면"
  },
  {
    "word": "빅샤크4바다공룡대모험"
  },
  {
    "word": "빅토리아로즈검정페인트"
  },
  {
    "word": "빅토리아로즈노랑페인트"
  },
  {
    "word": "빅토리아로즈녹색페인트"
  },
  {
    "word": "빅토리아로즈보라페인트"
  },
  {
    "word": "빅토리아로즈분홍페인트"
  },
  {
    "word": "빅토리아로즈빨강페인트"
  },
  {
    "word": "빅토리아로즈주황페인트"
  },
  {
    "word": "빅토리아로즈흰색페인트"
  },
  {
    "word": "빅토리아의동백꽃감상회"
  },
  {
    "word": "빅데이터분석컨설턴트"
  },
  {
    "word": "빅리본스타일백솜모카"
  },
  {
    "word": "빅마우스앤드어글리걸"
  },
  {
    "word": "빅쇼패밀리크리스마스"
  },
  {
    "word": "빅토리아처럼감아차라"
  },
  {
    "word": "빅팀버제재소를지켜라"
  },
  {
    "word": "빅히트트루데미지에코"
  },
  {
    "word": "빅2황금열쇠대소동"
  },
  {
    "word": "빅가나마일드초콜릿"
  },
  {
    "word": "빅고강서쪽의마그록"
  },
  {
    "word": "빅고호북쪽의마그록"
  },
  {
    "word": "빅누누리틀하이스트"
  },
  {
    "word": "빅데이대단한결혼식"
  },
  {
    "word": "빅데이터로보는세상"
  },
  {
    "word": "빅맥갱스터스앤골드"
  },
  {
    "word": "빅뽀로로제로딸기맛"
  },
  {
    "word": "빅뽀로로제로밀크맛"
  },
  {
    "word": "빅샤크2해저2만리"
  },
  {
    "word": "빅스가사랑한아시아"
  },
  {
    "word": "빅코미디크로스오버"
  },
  {
    "word": "빅토리아나무승강장"
  },
  {
    "word": "빅토리아로즈등장식"
  },
  {
    "word": "빅토리아로즈번호판"
  },
  {
    "word": "빅토리아와소원다리"
  },
  {
    "word": "빅토리아유령루시우"
  },
  {
    "word": "빅토리아의골드러시"
  },
  {
    "word": "빅휴즈기간틱캐논볼"
  },
  {
    "word": "빅데이터엔지니어"
  },
  {
    "word": "빅데이터컨설턴트"
  },
  {
    "word": "빅샤크매직체인지"
  },
  {
    "word": "빅이벤트베개싸움"
  },
  {
    "word": "빅컵누들매콤한맛"
  },
  {
    "word": "빅토라이즈부메랑"
  },
  {
    "word": "빅토리아로즈오라"
  },
  {
    "word": "빅토리아아일랜드"
  },
  {
    "word": "빅토리아인형에코"
  },
  {
    "word": "빅토리아중형택시"
  },
  {
    "word": "빅3볶음김치면"
  },
  {
    "word": "빅데이터분석가"
  },
  {
    "word": "빅데이터전문가"
  },
  {
    "word": "빅도어프라이즈"
  },
  {
    "word": "빅브라더팬클럽"
  },
  {
    "word": "빅브라더페도라"
  },
  {
    "word": "빅브릿지마이룸"
  },
  {
    "word": "빅스마일리보머"
  },
  {
    "word": "빅컵누들마라탕"
  },
  {
    "word": "빅컵누들우동맛"
  },
  {
    "word": "빅토라이즈뱅킹"
  },
  {
    "word": "빅토리그레이몬"
  },
  {
    "word": "빅토리아의부채"
  },
  {
    "word": "빅토리아하우스"
  },
  {
    "word": "빅피플페스티벌"
  },
  {
    "word": "빅하앜마양강습"
  },
  {
    "word": "빅가나마일드"
  },
  {
    "word": "빅고강의동굴"
  },
  {
    "word": "빅리드드래곤"
  },
  {
    "word": "빅리틀라이프"
  },
  {
    "word": "빅마마하우스"
  },
  {
    "word": "빅뽀로로제로"
  },
  {
    "word": "빅쿠리맨초코"
  },
  {
    "word": "빅터마이어법"
  },
  {
    "word": "빅토르의선물"
  },
  {
    "word": "빅토리스키드"
  },
  {
    "word": "빅토리아니즘"
  },
  {
    "word": "빅토리아랜드"
  },
  {
    "word": "빅토리아로즈"
  },
  {
    "word": "빅토리아사막"
  },
  {
    "word": "빅토리아스킨"
  },
  {
    "word": "빅토리아시대"
  },
  {
    "word": "빅토리아폭포"
  },
  {
    "word": "빅토리아호수"
  },
  {
    "word": "빅토리이천십"
  },
  {
    "word": "빅펜제트강습"
  },
  {
    "word": "빅플로앤올리"
  },
  {
    "word": "빅픽처패밀리"
  },
  {
    "word": "빅픽처하우스"
  },
  {
    "word": "빅글래숭이"
  },
  {
    "word": "빅데크바바"
  },
  {
    "word": "빅배드폭스"
  },
  {
    "word": "빅뱅보이스"
  },
  {
    "word": "빅버거가든"
  },
  {
    "word": "빅블린패널"
  },
  {
    "word": "빅샷게임쇼"
  },
  {
    "word": "빅쇼패밀리"
  },
  {
    "word": "빅스탈튤라"
  },
  {
    "word": "빅스파이더"
  },
  {
    "word": "빅아이디어"
  },
  {
    "word": "빅토리로드"
  },
  {
    "word": "빅토리아강"
  },
  {
    "word": "빅토리아론"
  },
  {
    "word": "빅토리아섬"
  },
  {
    "word": "빅토리아주"
  },
  {
    "word": "빅토리아호"
  },
  {
    "word": "빅토리차지"
  },
  {
    "word": "빅트리시티"
  },
  {
    "word": "빅파이딸기"
  },
  {
    "word": "빅풋주니어"
  },
  {
    "word": "빅피스골렘"
  },
  {
    "word": "빅하앜마양"
  },
  {
    "word": "빅고론도"
  },
  {
    "word": "빅마우스"
  },
  {
    "word": "빅몬스터"
  },
  {
    "word": "빅뱅에그"
  },
  {
    "word": "빅뱅태클"
  },
  {
    "word": "빅베이프"
  },
  {
    "word": "빅부메랑"
  },
  {
    "word": "빅브라더"
  },
  {
    "word": "빅스엘알"
  },
  {
    "word": "빅시스터"
  },
  {
    "word": "빅썬사과"
  },
  {
    "word": "빅웃코몬"
  },
  {
    "word": "빅웨이브"
  },
  {
    "word": "빅컨츄리"
  },
  {
    "word": "빅컵누들"
  },
  {
    "word": "빅콩알몬"
  },
  {
    "word": "빅쿠리맨"
  },
  {
    "word": "빅크런키"
  },
  {
    "word": "빅터브랜"
  },
  {
    "word": "빅토리아"
  },
  {
    "word": "빅펜제트"
  },
  {
    "word": "빅히어로"
  },
  {
    "word": "빅가나"
  },
  {
    "word": "빅게임"
  },
  {
    "word": "빅고강"
  },
  {
    "word": "빅고론"
  },
  {
    "word": "빅고호"
  },
  {
    "word": "빅나티"
  },
  {
    "word": "빅뉴스"
  },
  {
    "word": "빅다트"
  },
  {
    "word": "빅데기"
  },
  {
    "word": "빅데이"
  },
  {
    "word": "빅마마"
  },
  {
    "word": "빅마블"
  },
  {
    "word": "빅밴드"
  },
  {
    "word": "빅뱅설"
  },
  {
    "word": "빅뱅슛"
  },
  {
    "word": "빅버그"
  },
  {
    "word": "빅블루"
  },
  {
    "word": "빅블린"
  },
  {
    "word": "빅솔져"
  },
  {
    "word": "빅슬립"
  },
  {
    "word": "빅씨름"
  },
  {
    "word": "빅아이"
  },
  {
    "word": "빅애플"
  },
  {
    "word": "빅오더"
  },
  {
    "word": "빅오쇼"
  },
  {
    "word": "빅옥타"
  },
  {
    "word": "빅이슈"
  },
  {
    "word": "빅장질"
  },
  {
    "word": "빅크랙"
  },
  {
    "word": "빅토르"
  },
  {
    "word": "빅토리"
  },
  {
    "word": "빅트립"
  },
  {
    "word": "빅팀버"
  },
  {
    "word": "빅파이"
  },
  {
    "word": "빅포우"
  },
  {
    "word": "빅플로"
  },
  {
    "word": "빅피쉬"
  },
  {
    "word": "빅피프"
  },
  {
    "word": "빅픽처"
  },
  {
    "word": "빅헤드"
  },
  {
    "word": "빅다"
  },
  {
    "word": "빅맥"
  },
  {
    "word": "빅맨"
  },
  {
    "word": "빅뱅"
  },
  {
    "word": "빅벤"
  },
  {
    "word": "빅샷"
  },
  {
    "word": "빅셀"
  },
  {
    "word": "빅수"
  },
  {
    "word": "빅스"
  },
  {
    "word": "빅썬"
  },
  {
    "word": "빅알"
  },
  {
    "word": "빅장"
  },
  {
    "word": "빅터"
  },
  {
    "word": "빅톤"
  },
  {
    "word": "빅포"
  },
  {
    "word": "빅"
  }
]