[
  {
    "word": "일곱개의금인칙서원본일체와오스트리아국립도서관에소장된벤체슬라우스왕의호화필사본"
  },
  {
    "word": "일년안에1번은1상을1탈해서101퍼센트행복해지는일인들의이야기"
  },
  {
    "word": "일러스트레이티드맨문신을새긴사나이와열여덟편의이야기"
  },
  {
    "word": "일반공격이전체공격에2회공격인엄마는좋아하세요"
  },
  {
    "word": "일본목조건축물의보존과전승을위한전통기술과지식"
  },
  {
    "word": "일요일이좋다김병만정글의법칙인마다가스카르"
  },
  {
    "word": "일프티라몰타의납작한사워도우빵요리법과문화"
  },
  {
    "word": "일본군위안부문제해결을위한아시아연대회의"
  },
  {
    "word": "일본군위안부문제해결을위한정기수요시위"
  },
  {
    "word": "일본의메이지산업혁명유산철강조선및탄광"
  },
  {
    "word": "일퍼센트특별한재능있는아이재능없는아이"
  },
  {
    "word": "일본의장식수레축제야마호코야타이행사"
  },
  {
    "word": "일요일이좋다서바이벌오디션케이팝스타"
  },
  {
    "word": "일주일에한번클래스메이트를사는이야기"
  },
  {
    "word": "일요일이좋다김연아의키스앤드크라이"
  },
  {
    "word": "일요일이좋다다이어트서바이벌빅토리"
  },
  {
    "word": "일찍이마법소녀와악은적대하고있었다"
  },
  {
    "word": "일격으로끝내는최고속도의볼트태클"
  },
  {
    "word": "일곱명의집정관번개의신라이덴쇼군"
  },
  {
    "word": "일곱개의대죄브리타니아의여행자"
  },
  {
    "word": "일만마리물고기가산을날아오르다"
  },
  {
    "word": "일상속모던그레이웨어울프맛쿠키"
  },
  {
    "word": "일요음악여행세계음악하림입니다"
  },
  {
    "word": "일요일이좋다사돈처음뵙겠습니다"
  },
  {
    "word": "일월의스페셜레슨우아한새해맞이"
  },
  {
    "word": "일곱개의대죄빛에저주받은자들"
  },
  {
    "word": "일곱번째쿠키군단완성기념액자"
  },
  {
    "word": "일곱성인의소환시스템튜토리얼"
  },
  {
    "word": "일라이자슐레싱거베일을벗을래"
  },
  {
    "word": "일신상의이유로잠시휴재합니다"
  },
  {
    "word": "일심불란의화살은빗나가지않네"
  },
  {
    "word": "일월의스페셜레슨얼음레스토랑"
  },
  {
    "word": "일천칠백칠십육솔저세븐티식스"
  },
  {
    "word": "일곱개의대죄묵시록의4기사"
  },
  {
    "word": "일곱개의대죄원망의에든버러"
  },
  {
    "word": "일곱명의여인들과1건의살인"
  },
  {
    "word": "일곱성인의소환다인모드대전"
  },
  {
    "word": "일라이자슐라이싱어프리징핫"
  },
  {
    "word": "일라이자슐레싱거좀아는여자"
  },
  {
    "word": "일러스트와함께읽는세계명작"
  },
  {
    "word": "일렉트로고기꼬치구이곱빼기"
  },
  {
    "word": "일렉트로고기꼬치구이와버섯"
  },
  {
    "word": "일렉트로상급고기와생선구이"
  },
  {
    "word": "일렉트로생선꼬치구이와버섯"
  },
  {
    "word": "일렉트로특급고기와생선구이"
  },
  {
    "word": "일렉트리컬스트리머의전자포"
  },
  {
    "word": "일렉트릭스테이트키드코즈모"
  },
  {
    "word": "일만리바닷가자전거어촌여행"
  },
  {
    "word": "일반에너지드링크60에이피"
  },
  {
    "word": "일본도자기의신사기장이삼평"
  },
  {
    "word": "일산자두골농촌체험휴양마을"
  },
  {
    "word": "일요일이좋다골드미스가간다"
  },
  {
    "word": "일요일이좋다대결반전드라마"
  },
  {
    "word": "일우리가온종일하는바로그것"
  },
  {
    "word": "일월의스페셜레슨일본의새해"
  },
  {
    "word": "일자리창조프로젝트드림헌터"
  },
  {
    "word": "일촉즉발미궁을헤매는참가자"
  },
  {
    "word": "일화차시제로허니자몽블랙티"
  },
  {
    "word": "일곱시삼십이분코끼리열차"
  },
  {
    "word": "일단해봐요생방송오후1시"
  },
  {
    "word": "일라이자슐레싱거의쇼타임"
  },
  {
    "word": "일라이자슐레싱거핫포에버"
  },
  {
    "word": "일렉트로달걀프라이라이스"
  },
  {
    "word": "일렉트로상급고기소금구이"
  },
  {
    "word": "일렉트로상급짐승고기덮밥"
  },
  {
    "word": "일렉트로상급짐승스테이크"
  },
  {
    "word": "일렉트로특급고기소금구이"
  },
  {
    "word": "일렉트로특급짐승고기덮밥"
  },
  {
    "word": "일렉트로특급짐승스테이크"
  },
  {
    "word": "일루전스팅어일렉트릭쇼크"
  },
  {
    "word": "일물누가내아버지를죽였나"
  },
  {
    "word": "일반전술교육비디밀레니엄"
  },
  {
    "word": "일반전술교육비디백귀야행"
  },
  {
    "word": "일반전술교육비디붉은겨울"
  },
  {
    "word": "일반전술교육비디아리우스"
  },
  {
    "word": "일반전술교육비디아비도스"
  },
  {
    "word": "일반전술교육비디트리니티"
  },
  {
    "word": "일본의메이지산업혁명유산"
  },
  {
    "word": "일생에변태를세번만날확률"
  },
  {
    "word": "일억다운로드기념해피선물"
  },
  {
    "word": "일요스타워즈전화받으세요"
  },
  {
    "word": "일요일이좋다맨발의친구들"
  },
  {
    "word": "일요일이좋다아빠를부탁해"
  },
  {
    "word": "일요일이좋다패밀리가떴다"
  },
  {
    "word": "일월의스페셜레슨겨울여관"
  },
  {
    "word": "일월의스페셜레슨얼음나라"
  },
  {
    "word": "일일루돌프체험단팥맛쿠키"
  },
  {
    "word": "일화차시루이보스카라멜티"
  },
  {
    "word": "일곡경심모리아나고양이"
  },
  {
    "word": "일곱가지무기를가진헌터"
  },
  {
    "word": "일곱개의대죄계명의부활"
  },
  {
    "word": "일곱개의대죄분노의심판"
  },
  {
    "word": "일곱개의대죄성전의전조"
  },
  {
    "word": "일곱개의대죄천공의포로"
  },
  {
    "word": "일곱번째여름이남긴기적"
  },
  {
    "word": "일곱성인의소환규칙보기"
  },
  {
    "word": "일곱성인의소환규칙설명"
  },
  {
    "word": "일곱성인의소환손님도전"
  },
  {
    "word": "일곱성인의소환술집도전"
  },
  {
    "word": "일단은마츠리부정례회의"
  },
  {
    "word": "일러스트에디션제인에어"
  },
  {
    "word": "일레븐핑크다이아주사위"
  },
  {
    "word": "일렉트로고기와생선구이"
  },
  {
    "word": "일렉트로과일전골곱빼기"
  },
  {
    "word": "일렉트로상급치킨필래프"
  },
  {
    "word": "일렉트로플레인크레이프"
  },
  {
    "word": "일렉트로향긋한나물볶음"
  },
  {
    "word": "일렉트로향긋한버섯볶음"
  },
  {
    "word": "일로초등학교청망분교장"
  },
  {
    "word": "일루미네이션크리스마스"
  },
  {
    "word": "일반사회복지시설관리자"
  },
  {
    "word": "일반전술교육비디게헨나"
  },
  {
    "word": "일반전술교육비디발키리"
  },
  {
    "word": "일반전술교육비디산해경"
  },
  {
    "word": "일반전술교육비디선택권"
  },
  {
    "word": "일반전술교육비디추첨권"
  },
  {
    "word": "일본에어서오세요엘프씨"
  },
  {
    "word": "일본역사교과서왜곡사건"
  },
  {
    "word": "일본일주특급주사위게임"
  },
  {
    "word": "일부동산일등기용지주의"
  },
  {
    "word": "일산국제컨벤션고등학교"
  },
  {
    "word": "일어나라불면의밤을넘어"
  },
  {
    "word": "일요일아침유지원입니다"
  },
  {
    "word": "일요일이좋다인체탐험대"
  },
  {
    "word": "일월초등학교청기분교장"
  },
  {
    "word": "일주일만에사랑할순없다"
  },
  {
    "word": "일촌클리닉터놓고말해요"
  },
  {
    "word": "일컬어지는몽환다이긴죠"
  },
  {
    "word": "일하고일하고사랑을하고"
  },
  {
    "word": "일화차시유자민트티제로"
  },
  {
    "word": "일화차시제로키위그린티"
  },
  {
    "word": "일격에미간이격에심장"
  },
  {
    "word": "일곱개의타오르는우물"
  },
  {
    "word": "일단은달콤한휴식부터"
  },
  {
    "word": "일동레이크컨트리클럽"
  },
  {
    "word": "일라리블라시원앤온리"
  },
  {
    "word": "일러스트레이션학교수"
  },
  {
    "word": "일렉트로고기꼬치구이"
  },
  {
    "word": "일렉트로고기밀크수프"
  },
  {
    "word": "일렉트로고기소금구이"
  },
  {
    "word": "일렉트로과일버섯무침"
  },
  {
    "word": "일렉트로몬스터주먹밥"
  },
  {
    "word": "일렉트로몬스터케이크"
  },
  {
    "word": "일렉트로버섯꼬치구이"
  },
  {
    "word": "일렉트로버섯밀크수프"
  },
  {
    "word": "일렉트로버섯소금구이"
  },
  {
    "word": "일렉트로버터바른사과"
  },
  {
    "word": "일렉트로상급고기스튜"
  },
  {
    "word": "일렉트로상급고기카레"
  },
  {
    "word": "일렉트로상급치킨카레"
  },
  {
    "word": "일렉트로생선꼬치구이"
  },
  {
    "word": "일렉트로생선뫼니에르"
  },
  {
    "word": "일렉트로생선밀크수프"
  },
  {
    "word": "일렉트로생선소금구이"
  },
  {
    "word": "일렉트로야채밀크수프"
  },
  {
    "word": "일렉트로야채소금구이"
  },
  {
    "word": "일렉트로짐승고기덮밥"
  },
  {
    "word": "일렉트로짐승고기카레"
  },
  {
    "word": "일렉트로짐승스테이크"
  },
  {
    "word": "일렉트로커뮤니케이션"
  },
  {
    "word": "일렉트로키이스의눈알"
  },
  {
    "word": "일렉트로특급고기스튜"
  },
  {
    "word": "일렉트로특급고기카레"
  },
  {
    "word": "일렉트로특급치킨카레"
  },
  {
    "word": "일렉트로파이어마법사"
  },
  {
    "word": "일렉트로프루트케이크"
  },
  {
    "word": "일렉트릭버스터크로스"
  },
  {
    "word": "일렉트릭퍼플트레이서"
  },
  {
    "word": "일루전스팅어이레귤러"
  },
  {
    "word": "일룰리사트얼음피오르"
  },
  {
    "word": "일명털의습격발모크림"
  },
  {
    "word": "일모계등시천한조입첨"
  },
  {
    "word": "일모창산원천한백옥빈"
  },
  {
    "word": "일반기술노트밀레니엄"
  },
  {
    "word": "일반기술노트백귀야행"
  },
  {
    "word": "일반기술노트붉은겨울"
  },
  {
    "word": "일반기술노트아리우스"
  },
  {
    "word": "일반기술노트아비도스"
  },
  {
    "word": "일반기술노트트리니티"
  },
  {
    "word": "일반사업체경리사무원"
  },
  {
    "word": "일반수자조종공작기계"
  },
  {
    "word": "일번악극바람을타는깃"
  },
  {
    "word": "일본상공에어서오세요"
  },
  {
    "word": "일본천황암살미수사건"
  },
  {
    "word": "일부러만든생크림수염"
  },
  {
    "word": "일상순찰속즐거운일들"
  },
  {
    "word": "일상의지식어쩌다어른"
  },
  {
    "word": "일신여자상업고등학교"
  },
  {
    "word": "일억곡예사의상속문서"
  },
  {
    "word": "일억독수리의건설장비"
  },
  {
    "word": "일요음악여행영화음악"
  },
  {
    "word": "일요일이좋다꽃놀이패"
  },
  {
    "word": "일요일이좋다룸메이트"
  },
  {
    "word": "일요일이좋다영웅호걸"
  },
  {
    "word": "일월식달의축제제이나"
  },
  {
    "word": "일월천년경강산만고병"
  },
  {
    "word": "일일노움마법사맛쿠키"
  },
  {
    "word": "일일부독서구중생형극"
  },
  {
    "word": "일제강점기군산역사관"
  },
  {
    "word": "일진만화에서살아남기"
  },
  {
    "word": "일출숙무개월출천하백"
  },
  {
    "word": "일하고싸우고사랑하라"
  },
  {
    "word": "일학년이되어버린다면"
  },
  {
    "word": "일호패배자가될수없어"
  },
  {
    "word": "일화차시고구마알밤차"
  },
  {
    "word": "일확천금을노리는승객"
  },
  {
    "word": "일강김철선생기념관"
  },
  {
    "word": "일격살충호이호이씨"
  },
  {
    "word": "일곱개의고딕이야기"
  },
  {
    "word": "일곱번째내가죽던날"
  },
  {
    "word": "일곱색깔목소리사탕"
  },
  {
    "word": "일곱영웅에관한비석"
  },
  {
    "word": "일구일삼송정역시장"
  },
  {
    "word": "일구팔칠영화촬영지"
  },
  {
    "word": "일급기밀공학연구소"
  },
  {
    "word": "일단정지눈꽃주사위"
  },
  {
    "word": "일단정지유령주사위"
  },
  {
    "word": "일도사랑도인사부터"
  },
  {
    "word": "일라이자슐라이싱어"
  },
  {
    "word": "일람후정기출급어음"
  },
  {
    "word": "일러스트레이티드맨"
  },
  {
    "word": "일러스트자기앞의생"
  },
  {
    "word": "일러스트파이이야기"
  },
  {
    "word": "일레븐아토믹주사위"
  },
  {
    "word": "일레즌의사탕엑스엘"
  },
  {
    "word": "일렉트로고기쌈구이"
  },
  {
    "word": "일렉트로고기주먹밥"
  },
  {
    "word": "일렉트로너츠케이크"
  },
  {
    "word": "일렉트로달걀프라이"
  },
  {
    "word": "일렉트로몬스터수프"
  },
  {
    "word": "일렉트로몬스터전골"
  },
  {
    "word": "일렉트로몬스터카레"
  },
  {
    "word": "일렉트로버섯리조또"
  },
  {
    "word": "일렉트로버섯쌈구이"
  },
  {
    "word": "일렉트로버섯오믈렛"
  },
  {
    "word": "일렉트로버섯주먹밥"
  },
  {
    "word": "일렉트로사파리파크"
  },
  {
    "word": "일렉트로생선쌈구이"
  },
  {
    "word": "일렉트로야채오믈렛"
  },
  {
    "word": "일렉트로야채주먹밥"
  },
  {
    "word": "일렉트로에그타르트"
  },
  {
    "word": "일렉트로조아의위돌"
  },
  {
    "word": "일렉트로치킨필래프"
  },
  {
    "word": "일렉트로카레라이스"
  },
  {
    "word": "일렉트로카레필래프"
  },
  {
    "word": "일렉트로토끼드래곤"
  },
  {
    "word": "일렉트로프루트파이"
  },
  {
    "word": "일렉트로해물주먹밥"
  },
  {
    "word": "일루저너리블래스트"
  },
  {
    "word": "일루전스팅어디센트"
  },
  {
    "word": "일루전스팅어메테오"
  },
  {
    "word": "일리아스오디세이아"
  },
  {
    "word": "일리야드들판끝자락"
  },
  {
    "word": "일리야드들판어딘가"
  },
  {
    "word": "일반기술노트게헨나"
  },
  {
    "word": "일반기술노트발키리"
  },
  {
    "word": "일반기술노트산해경"
  },
  {
    "word": "일반기술노트선택권"
  },
  {
    "word": "일반기술노트추첨권"
  },
  {
    "word": "일반사회교육학교수"
  },
  {
    "word": "일반제조용마테리얼"
  },
  {
    "word": "일반철도설계기술자"
  },
  {
    "word": "일방적커뮤니케이션"
  },
  {
    "word": "일본군위안부역사관"
  },
  {
    "word": "일부러휘갈겨쓴글씨"
  },
  {
    "word": "일산화탄소산화세균"
  },
  {
    "word": "일상생활가능하세요"
  },
  {
    "word": "일상에숨어있는함정"
  },
  {
    "word": "일센티미터의자존심"
  },
  {
    "word": "일심정토의주인에이"
  },
  {
    "word": "일안리플렉스카메라"
  },
  {
    "word": "일어나서처음하는것"
  },
  {
    "word": "일억일단정지경찰차"
  },
  {
    "word": "일요음악여행클래식"
  },
  {
    "word": "일요일이좋다기승사"
  },
  {
    "word": "일요특선다큐멘터리"
  },
  {
    "word": "일월수다라니주머니"
  },
  {
    "word": "일월식달의축제리리"
  },
  {
    "word": "일일구메모리얼데이"
  },
  {
    "word": "일일구항공구조대원"
  },
  {
    "word": "일일노움딸기맛쿠키"
  },
  {
    "word": "일일눈사람산타모자"
  },
  {
    "word": "일일용사공주맛쿠키"
  },
  {
    "word": "일임매매투자자문가"
  },
  {
    "word": "일제강점기건축물들"
  },
  {
    "word": "일제강점기보물찾기"
  },
  {
    "word": "일주일의결권의원칙"
  },
  {
    "word": "일죽시외버스터미널"
  },
  {
    "word": "일차세계대전전투기"
  },
  {
    "word": "일천만개헌서명운동"
  },
  {
    "word": "일초에한방울어믹스"
  },
  {
    "word": "일출의모래독무용단"
  },
  {
    "word": "일컬어지는괴력난신"
  },
  {
    "word": "일거리가있다던데"
  },
  {
    "word": "일곱개의고양이눈"
  },
  {
    "word": "일곱명의술래잡기"
  },
  {
    "word": "일곱현인의의정서"
  },
  {
    "word": "일공구별일다있네"
  },
  {
    "word": "일과성상황성장애"
  },
  {
    "word": "일급비밀업무일지"
  },
  {
    "word": "일년을기다린상대"
  },
  {
    "word": "일년차만렙매니저"
  },
  {
    "word": "일단먼저하고싶어"
  },
  {
    "word": "일단정지커주사위"
  },
  {
    "word": "일대삼천대천세계"
  },
  {
    "word": "일동제일유황온천"
  },
  {
    "word": "일등복권구출작전"
  },
  {
    "word": "일라이자슐레싱거"
  },
  {
    "word": "일라이자확인사살"
  },
  {
    "word": "일러스트연금술사"
  },
  {
    "word": "일레븐진주주사위"
  },
  {
    "word": "일렉킥파이팅포터"
  },
  {
    "word": "일렉트로고기스튜"
  },
  {
    "word": "일렉트로과일전골"
  },
  {
    "word": "일렉트로닉스모그"
  },
  {
    "word": "일렉트로닉컴퓨터"
  },
  {
    "word": "일렉트로달걀푸딩"
  },
  {
    "word": "일렉트로미트파이"
  },
  {
    "word": "일렉트로블래스트"
  },
  {
    "word": "일렉트로세라믹스"
  },
  {
    "word": "일렉트로애플파이"
  },
  {
    "word": "일렉트로야채구이"
  },
  {
    "word": "일렉트로옵틱효과"
  },
  {
    "word": "일렉트로치킨카레"
  },
  {
    "word": "일렉트로피시파이"
  },
  {
    "word": "일렉트론블라스터"
  },
  {
    "word": "일렉트리컬피스트"
  },
  {
    "word": "일렉트릭쇼크큐브"
  },
  {
    "word": "일렉트릭스테이트"
  },
  {
    "word": "일루미네이션트리"
  },
  {
    "word": "일리단스톰레이지"
  },
  {
    "word": "일리언파이프연주"
  },
  {
    "word": "일반직원보안요원"
  },
  {
    "word": "일반직원현장요원"
  },
  {
    "word": "일반합성용기동석"
  },
  {
    "word": "일번국도를달려라"
  },
  {
    "word": "일본뇌염바이러스"
  },
  {
    "word": "일본에서보물찾기"
  },
  {
    "word": "일본여행다이어리"
  },
  {
    "word": "일본침몰이천이십"
  },
  {
    "word": "일분요리뚝딱이형"
  },
  {
    "word": "일산대진고등학교"
  },
  {
    "word": "일산은행초등학교"
  },
  {
    "word": "일산화탄소혈색소"
  },
  {
    "word": "일삼일팔의몽정기"
  },
  {
    "word": "일상모임의편안함"
  },
  {
    "word": "일신여자고등학교"
  },
  {
    "word": "일어수출입영업원"
  },
  {
    "word": "일억추격자의헬멧"
  },
  {
    "word": "일요음악여행가요"
  },
  {
    "word": "일월부터유월까지"
  },
  {
    "word": "일월영측진수열장"
  },
  {
    "word": "일월의소나무배경"
  },
  {
    "word": "일을추진하는남자"
  },
  {
    "word": "일이삼컨트리클럽"
  },
  {
    "word": "일일사전화안내원"
  },
  {
    "word": "일일삼회덤벨세트"
  },
  {
    "word": "일자리수석비서관"
  },
  {
    "word": "일주년기념번호판"
  },
  {
    "word": "일주년기념스키드"
  },
  {
    "word": "일주년기념테두리"
  },
  {
    "word": "일진에게찍혔을때"
  },
  {
    "word": "일차반응기조작원"
  },
  {
    "word": "일차원이되고싶어"
  },
  {
    "word": "일처리는원칙대로"
  },
  {
    "word": "일촉즉발테러리즘"
  },
  {
    "word": "일탈자들의무애광"
  },
  {
    "word": "일퍼센트의어떤것"
  },
  {
    "word": "일품해물라면왕컵"
  },
  {
    "word": "일하는땅콩햄스터"
  },
  {
    "word": "일하지않는두사람"
  },
  {
    "word": "일화옥수수수염차"
  },
  {
    "word": "일화차시유근피차"
  },
  {
    "word": "일화차시호박팥차"
  },
  {
    "word": "일화청포도에이드"
  },
  {
    "word": "일확천금골드러시"
  },
  {
    "word": "일회용동력캐논포"
  },
  {
    "word": "일간조절발전소"
  },
  {
    "word": "일곱겹관통화살"
  },
  {
    "word": "일곱번죽은남자"
  },
  {
    "word": "일곱빛깔드롭스"
  },
  {
    "word": "일곱성인의창술"
  },
  {
    "word": "일곱시에들어줘"
  },
  {
    "word": "일곱점무당벌레"
  },
  {
    "word": "일과성알칼리요"
  },
  {
    "word": "일그러진알현실"
  },
  {
    "word": "일급비밀스파이"
  },
  {
    "word": "일단동굴로피난"
  },
  {
    "word": "일단정지경찰차"
  },
  {
    "word": "일더하기이삼림"
  },
  {
    "word": "일독이삼국동맹"
  },
  {
    "word": "일등은내차지야"
  },
  {
    "word": "일라이자의기적"
  },
  {
    "word": "일러스트레이션"
  },
  {
    "word": "일러스트레이터"
  },
  {
    "word": "일렉토끼등장식"
  },
  {
    "word": "일렉트로과일찜"
  },
  {
    "word": "일렉트로그래프"
  },
  {
    "word": "일렉트로마이트"
  },
  {
    "word": "일렉트로이드척"
  },
  {
    "word": "일렉트로이벤트"
  },
  {
    "word": "일렉트로타이프"
  },
  {
    "word": "일렉트로핫밀크"
  },
  {
    "word": "일렉트론영웅전"
  },
  {
    "word": "일렉트릭디퓨젼"
  },
  {
    "word": "일렉트릭메이커"
  },
  {
    "word": "일렉트릭바인드"
  },
  {
    "word": "일로동초등학교"
  },
  {
    "word": "일리아의목걸이"
  },
  {
    "word": "일물일가의법칙"
  },
  {
    "word": "일반구간방조제"
  },
  {
    "word": "일반상대성이론"
  },
  {
    "word": "일반수문지질학"
  },
  {
    "word": "일반언어학강의"
  },
  {
    "word": "일반용뜨락또르"
  },
  {
    "word": "일반적가치형태"
  },
  {
    "word": "일반촬영용필름"
  },
  {
    "word": "일반화통행비용"
  },
  {
    "word": "일반활동보고서"
  },
  {
    "word": "일반회선시험원"
  },
  {
    "word": "일발필중플러스"
  },
  {
    "word": "일밤아빠어디가"
  },
  {
    "word": "일방적저촉규정"
  },
  {
    "word": "일백삼십육지옥"
  },
  {
    "word": "일본가시날도래"
  },
  {
    "word": "일본문학연구원"
  },
  {
    "word": "일본식성명강요"
  },
  {
    "word": "일본인납북사건"
  },
  {
    "word": "일본인납치사건"
  },
  {
    "word": "일본주혈흡충증"
  },
  {
    "word": "일사천리플러스"
  },
  {
    "word": "일산동고등학교"
  },
  {
    "word": "일산양일중학교"
  },
  {
    "word": "일산화망가니즈"
  },
  {
    "word": "일산화비스무트"
  },
  {
    "word": "일산화타이타늄"
  },
  {
    "word": "일산화탄소세균"
  },
  {
    "word": "일산화탄소중독"
  },
  {
    "word": "일상으로의초대"
  },
  {
    "word": "일상을연주하라"
  },
  {
    "word": "일식요리사쇼우"
  },
  {
    "word": "일신여자중학교"
  },
  {
    "word": "일어나라용사여"
  },
  {
    "word": "일어나요강귀찬"
  },
  {
    "word": "일어무역영업원"
  },
  {
    "word": "일어서서사우나"
  },
  {
    "word": "일어일문학교수"
  },
  {
    "word": "일어해외영업원"
  },
  {
    "word": "일영노랑페인트"
  },
  {
    "word": "일요음악여행팝"
  },
  {
    "word": "일요일의딸기짱"
  },
  {
    "word": "일요진단라이브"
  },
  {
    "word": "일우스님의믿음"
  },
  {
    "word": "일원이차방정식"
  },
  {
    "word": "일원일차방정식"
  },
  {
    "word": "일원화계획체계"
  },
  {
    "word": "일인용간이천막"
  },
  {
    "word": "일인크리에이터"
  },
  {
    "word": "일일전출정준비"
  },
  {
    "word": "일자활개펴기춤"
  },
  {
    "word": "일자후정기출급"
  },
  {
    "word": "일장기말살사건"
  },
  {
    "word": "일전불사플러스"
  },
  {
    "word": "일정성분비법칙"
  },
  {
    "word": "일정조성의법칙"
  },
  {
    "word": "일주년기념오라"
  },
  {
    "word": "일주년기념헤어"
  },
  {
    "word": "일죽버스터미널"
  },
  {
    "word": "일진머티리얼즈"
  },
  {
    "word": "일차계통계기원"
  },
  {
    "word": "일차대전폭격기"
  },
  {
    "word": "일차여러마디식"
  },
  {
    "word": "일차적준비자산"
  },
  {
    "word": "일치차이병용법"
  },
  {
    "word": "일타강사백사부"
  },
  {
    "word": "일퍼센트의기적"
  },
  {
    "word": "일품해물라면컵"
  },
  {
    "word": "일필삼십오억원"
  },
  {
    "word": "일필일용지주의"
  },
  {
    "word": "일하는세포블랙"
  },
  {
    "word": "일할시간입니다"
  },
  {
    "word": "일호가될순없어"
  },
  {
    "word": "일화레몬에이드"
  },
  {
    "word": "일화키위에이드"
  },
  {
    "word": "일개어혼전천"
  },
  {
    "word": "일거수일투족"
  },
  {
    "word": "일고수이명창"
  },
  {
    "word": "일곡초등학교"
  },
  {
    "word": "일곱개의회의"
  },
  {
    "word": "일곱동갈망둑"
  },
  {
    "word": "일곱명의포로"
  },
  {
    "word": "일곱목가래질"
  },
  {
    "word": "일곱목한카래"
  },
  {
    "word": "일곱박공의집"
  },
  {
    "word": "일곱번째감각"
  },
  {
    "word": "일곱번째파도"
  },
  {
    "word": "일곱잇단음표"
  },
  {
    "word": "일과이분의일"
  },
  {
    "word": "일광변조보살"
  },
  {
    "word": "일광절약시간"
  },
  {
    "word": "일광초등학교"
  },
  {
    "word": "일광해수욕장"
  },
  {
    "word": "일국사회주의"
  },
  {
    "word": "일국일당원칙"
  },
  {
    "word": "일국일표주의"
  },
  {
    "word": "일기분열조직"
  },
  {
    "word": "일기죽얄기죽"
  },
  {
    "word": "일기죽일기죽"
  },
  {
    "word": "일년365일"
  },
  {
    "word": "일단사일두갱"
  },
  {
    "word": "일단사일표음"
  },
  {
    "word": "일단시작해봐"
  },
  {
    "word": "일대삼천세계"
  },
  {
    "word": "일도양단유키"
  },
  {
    "word": "일도초등학교"
  },
  {
    "word": "일독방공협정"
  },
  {
    "word": "일동고등학교"
  },
  {
    "word": "일동초등학교"
  },
  {
    "word": "일등항해사팽"
  },
  {
    "word": "일라리블라시"
  },
  {
    "word": "일란성쌍둥이"
  },
  {
    "word": "일란성쌍생아"
  },
  {
    "word": "일람출급어음"
  },
  {
    "word": "일래스틱직물"
  },
  {
    "word": "일렁이는운해"
  },
  {
    "word": "일레도리자드"
  },
  {
    "word": "일레즌의사탕"
  },
  {
    "word": "일렉트로닉스"
  },
  {
    "word": "일렉트로달걀"
  },
  {
    "word": "일렉트로모드"
  },
  {
    "word": "일렉트로물약"
  },
  {
    "word": "일렉트로밀빵"
  },
  {
    "word": "일렉트로부츠"
  },
  {
    "word": "일렉트로제트"
  },
  {
    "word": "일렉트로조아"
  },
  {
    "word": "일렉트론메탈"
  },
  {
    "word": "일렉트론볼트"
  },
  {
    "word": "일렉트릭뮤직"
  },
  {
    "word": "일렉트릭쇼크"
  },
  {
    "word": "일렉트릭차지"
  },
  {
    "word": "일렉황다랑어"
  },
  {
    "word": "일로초등학교"
  },
  {
    "word": "일루미네이션"
  },
  {
    "word": "일루셔니스트"
  },
  {
    "word": "일루저닉쏜즈"
  },
  {
    "word": "일류로가는길"
  },
  {
    "word": "일리걸컬렉션"
  },
  {
    "word": "일리미네이터"
  },
  {
    "word": "일리있는사랑"
  },
  {
    "word": "일물일권주의"
  },
  {
    "word": "일반경쟁계약"
  },
  {
    "word": "일반경제법칙"
  },
  {
    "word": "일반공격펑펑"
  },
  {
    "word": "일반공작기계"
  },
  {
    "word": "일반권력관계"
  },
  {
    "word": "일반권리능력"
  },
  {
    "word": "일반균형분석"
  },
  {
    "word": "일반균형이론"
  },
  {
    "word": "일반노동조합"
  },
  {
    "word": "일반무이능력"
  },
  {
    "word": "일반물가지수"
  },
  {
    "word": "일반병종부대"
  },
  {
    "word": "일반사회교사"
  },
  {
    "word": "일반소환두배"
  },
  {
    "word": "일반적구속력"
  },
  {
    "word": "일반적등가물"
  },
  {
    "word": "일반전화통신"
  },
  {
    "word": "일반조합능력"
  },
  {
    "word": "일반지식교육"
  },
  {
    "word": "일반직공무원"
  },
  {
    "word": "일반쿠키상자"
  },
  {
    "word": "일반통치관계"
  },
  {
    "word": "일반파산주의"
  },
  {
    "word": "일반회계예산"
  },
  {
    "word": "일반횡선수표"
  },
  {
    "word": "일반휘장상자"
  },
  {
    "word": "일밤애니멀즈"
  },
  {
    "word": "일방심리주의"
  },
  {
    "word": "일방심문주의"
  },
  {
    "word": "일방적상행위"
  },
  {
    "word": "일벌백계주의"
  },
  {
    "word": "일본군위안부"
  },
  {
    "word": "일본노래기벌"
  },
  {
    "word": "일본말발도리"
  },
  {
    "word": "일본사시나무"
  },
  {
    "word": "일본쌍자흡충"
  },
  {
    "word": "일본어연구원"
  },
  {
    "word": "일본어통역사"
  },
  {
    "word": "일본어학교수"
  },
  {
    "word": "일본올벚나무"
  },
  {
    "word": "일본일본바지"
  },
  {
    "word": "일본잎갈나무"
  },
  {
    "word": "일본조팝나무"
  },
  {
    "word": "일본주혈흡충"
  },
  {
    "word": "일부다처주의"
  },
  {
    "word": "일부러스럽다"
  },
  {
    "word": "일부일부주의"
  },
  {
    "word": "일부일처주의"
  },
  {
    "word": "일분이지나면"
  },
  {
    "word": "일불이살육통"
  },
  {
    "word": "일산가구단지"
  },
  {
    "word": "일산고등학교"
  },
  {
    "word": "일산동중학교"
  },
  {
    "word": "일산살대투겁"
  },
  {
    "word": "일산초등학교"
  },
  {
    "word": "일산해수욕장"
  },
  {
    "word": "일산호수공원"
  },
  {
    "word": "일산화이질소"
  },
  {
    "word": "일산화일질소"
  },
  {
    "word": "일산화코발트"
  },
  {
    "word": "일승월항지곡"
  },
  {
    "word": "일시플랑크톤"
  },
  {
    "word": "일식일리아리"
  },
  {
    "word": "일식총주방장"
  },
  {
    "word": "일신초등학교"
  },
  {
    "word": "일억불고양이"
  },
  {
    "word": "일요음악여행"
  },
  {
    "word": "일요일의철학"
  },
  {
    "word": "일요일이좋다"
  },
  {
    "word": "일운초등학교"
  },
  {
    "word": "일원적국가론"
  },
  {
    "word": "일원적이주제"
  },
  {
    "word": "일월초등학교"
  },
  {
    "word": "일이너무잘돼"
  },
  {
    "word": "일이산화질소"
  },
  {
    "word": "일인일당주의"
  },
  {
    "word": "일일구리믹스"
  },
  {
    "word": "일일보안결산"
  },
  {
    "word": "일자턱솔이음"
  },
  {
    "word": "일정항터미널"
  },
  {
    "word": "일제병탄조약"
  },
  {
    "word": "일주광행로차"
  },
  {
    "word": "일주년케이크"
  },
  {
    "word": "일주일간친구"
  },
  {
    "word": "일죽고등학교"
  },
  {
    "word": "일죽초등학교"
  },
  {
    "word": "일직초등학교"
  },
  {
    "word": "일진과의전쟁"
  },
  {
    "word": "일차근사이론"
  },
  {
    "word": "일차봉사단위"
  },
  {
    "word": "일차안같기식"
  },
  {
    "word": "일차원적인간"
  },
  {
    "word": "일차의료봉사"
  },
  {
    "word": "일차전기설비"
  },
  {
    "word": "일차전자방출"
  },
  {
    "word": "일차측정요소"
  },
  {
    "word": "일차탄소원자"
  },
  {
    "word": "일차표준물질"
  },
  {
    "word": "일초에한방울"
  },
  {
    "word": "일출봉유채밭"
  },
  {
    "word": "일층소수파련"
  },
  {
    "word": "일층지하일층"
  },
  {
    "word": "일타이피술법"
  },
  {
    "word": "일탈하는용기"
  },
  {
    "word": "일트로바토레"
  },
  {
    "word": "일품삼선짜장"
  },
  {
    "word": "일품해물라면"
  },
  {
    "word": "일하러가야돼"
  },
  {
    "word": "일행천리전술"
  },
  {
    "word": "일화오미지교"
  },
  {
    "word": "일화헛개꿀물"
  },
  {
    "word": "일회용동력팔"
  },
  {
    "word": "일회용보호벽"
  },
  {
    "word": "일회우상복엽"
  },
  {
    "word": "일가알코올"
  },
  {
    "word": "일가염색체"
  },
  {
    "word": "일각돌고래"
  },
  {
    "word": "일각수자리"
  },
  {
    "word": "일거무소식"
  },
  {
    "word": "일경수세법"
  },
  {
    "word": "일고여덟째"
  },
  {
    "word": "일곡중학교"
  },
  {
    "word": "일곱난쟁이"
  },
  {
    "word": "일곱달내기"
  },
  {
    "word": "일곱번째방"
  },
  {
    "word": "일곱색의독"
  },
  {
    "word": "일곱톤바리"
  },
  {
    "word": "일과감인관"
  },
  {
    "word": "일과이의틈"
  },
  {
    "word": "일관메이커"
  },
  {
    "word": "일광건조법"
  },
  {
    "word": "일광반사경"
  },
  {
    "word": "일광중학교"
  },
  {
    "word": "일급근로자"
  },
  {
    "word": "일급선거인"
  },
  {
    "word": "일기도기호"
  },
  {
    "word": "일기예보학"
  },
  {
    "word": "일기체소설"
  },
  {
    "word": "일기화삼찬"
  },
  {
    "word": "일꾼곰젤리"
  },
  {
    "word": "일난풍화사"
  },
  {
    "word": "일년빗자루"
  },
  {
    "word": "일년생식물"
  },
  {
    "word": "일년생초본"
  },
  {
    "word": "일년정거장"
  },
  {
    "word": "일념무량겁"
  },
  {
    "word": "일념미타불"
  },
  {
    "word": "일념오백생"
  },
  {
    "word": "일단계유통"
  },
  {
    "word": "일당독재제"
  },
  {
    "word": "일대다대응"
  },
  {
    "word": "일대비교법"
  },
  {
    "word": "일대사인연"
  },
  {
    "word": "일대일대응"
  },
  {
    "word": "일대일변환"
  },
  {
    "word": "일대일사상"
  },
  {
    "word": "일동장유가"
  },
  {
    "word": "일동중학교"
  },
  {
    "word": "일등기관사"
  },
  {
    "word": "일등주사위"
  },
  {
    "word": "일등항해사"
  },
  {
    "word": "일란성쌍태"
  },
  {
    "word": "일람불어음"
  },
  {
    "word": "일런드영양"
  },
  {
    "word": "일렁이는달"
  },
  {
    "word": "일레븐세트"
  },
  {
    "word": "일렉금눈돔"
  },
  {
    "word": "일렉트릭윙"
  },
  {
    "word": "일로카노족"
  },
  {
    "word": "일론머스크"
  },
  {
    "word": "일루전캣맨"
  },
  {
    "word": "일류건강식"
  },
  {
    "word": "일리노이주"
  },
  {
    "word": "일리마니산"
  },
  {
    "word": "일리천전투"
  },
  {
    "word": "일만의정서"
  },
  {
    "word": "일말의순정"
  },
  {
    "word": "일메나대지"
  },
  {
    "word": "일메나연못"
  },
  {
    "word": "일모작전답"
  },
  {
    "word": "일목삼악발"
  },
  {
    "word": "일몰베리티"
  },
  {
    "word": "일몰붕어빵"
  },
  {
    "word": "일문에디터"
  },
  {
    "word": "일문일답식"
  },
  {
    "word": "일반강화석"
  },
  {
    "word": "일반거래세"
  },
  {
    "word": "일반경기자"
  },
  {
    "word": "일반관리비"
  },
  {
    "word": "일반국가학"
  },
  {
    "word": "일반물리학"
  },
  {
    "word": "일반사면령"
  },
  {
    "word": "일반삼토포"
  },
  {
    "word": "일반생리학"
  },
  {
    "word": "일반선거권"
  },
  {
    "word": "일반소비세"
  },
  {
    "word": "일반신화학"
  },
  {
    "word": "일반심리학"
  },
  {
    "word": "일반양념장"
  },
  {
    "word": "일반언어학"
  },
  {
    "word": "일반우선권"
  },
  {
    "word": "일반의미론"
  },
  {
    "word": "일반적도야"
  },
  {
    "word": "일반적선거"
  },
  {
    "word": "일반적지도"
  },
  {
    "word": "일반지리학"
  },
  {
    "word": "일반참모부"
  },
  {
    "word": "일반탁아소"
  },
  {
    "word": "일반폐기물"
  },
  {
    "word": "일반행정사"
  },
  {
    "word": "일발인천균"
  },
  {
    "word": "일방적이야"
  },
  {
    "word": "일방통행로"
  },
  {
    "word": "일변도정책"
  },
  {
    "word": "일본동면쥐"
  },
  {
    "word": "일본알프스"
  },
  {
    "word": "일본어강사"
  },
  {
    "word": "일본어교사"
  },
  {
    "word": "일본오엽송"
  },
  {
    "word": "일본오징어"
  },
  {
    "word": "일본원숭이"
  },
  {
    "word": "일본전나무"
  },
  {
    "word": "일본쥐벼룩"
  },
  {
    "word": "일본풍카페"
  },
  {
    "word": "일본학교수"
  },
  {
    "word": "일본할미꽃"
  },
  {
    "word": "일부구성문"
  },
  {
    "word": "일부다처제"
  },
  {
    "word": "일부러스레"
  },
  {
    "word": "일부변경선"
  },
  {
    "word": "일부분형식"
  },
  {
    "word": "일부일부제"
  },
  {
    "word": "일부일처제"
  },
  {
    "word": "일부주권국"
  },
  {
    "word": "일부하곡선"
  },
  {
    "word": "일분모회록"
  },
  {
    "word": "일분부거행"
  },
  {
    "word": "일분부시행"
  },
  {
    "word": "일분자반응"
  },
  {
    "word": "일불이보살"
  },
  {
    "word": "일사부재리"
  },
  {
    "word": "일사부재의"
  },
  {
    "word": "일산갈고리"
  },
  {
    "word": "일산대꼭지"
  },
  {
    "word": "일산중학교"
  },
  {
    "word": "일산화망간"
  },
  {
    "word": "일산화질소"
  },
  {
    "word": "일산화창연"
  },
  {
    "word": "일산화크롬"
  },
  {
    "word": "일산화탄소"
  },
  {
    "word": "일산화티탄"
  },
  {
    "word": "일상다반사"
  },
  {
    "word": "일상다정사"
  },
  {
    "word": "일상적인삶"
  },
  {
    "word": "일색고사리"
  },
  {
    "word": "일석이츄츄"
  },
  {
    "word": "일성이사금"
  },
  {
    "word": "일성정시의"
  },
  {
    "word": "일승현성교"
  },
  {
    "word": "일시귀휴제"
  },
  {
    "word": "일시금보험"
  },
  {
    "word": "일시불공채"
  },
  {
    "word": "일시불대부"
  },
  {
    "word": "일시불보험"
  },
  {
    "word": "일시차입금"
  },
  {
    "word": "일식조리사"
  },
  {
    "word": "일식한계각"
  },
  {
    "word": "일신전속권"
  },
  {
    "word": "일신중학교"
  },
  {
    "word": "일실의원종"
  },
  {
    "word": "일심불란히"
  },
  {
    "word": "일어나보니"
  },
  {
    "word": "일어번역가"
  },
  {
    "word": "일언이폐지"
  },
  {
    "word": "일엽쌍곡면"
  },
  {
    "word": "일엽쌍곡선"
  },
  {
    "word": "일요매거진"
  },
  {
    "word": "일요시네마"
  },
  {
    "word": "일요일의병"
  },
  {
    "word": "일용근로자"
  },
  {
    "word": "일원방정식"
  },
  {
    "word": "일원자분자"
  },
  {
    "word": "일월과거사"
  },
  {
    "word": "일월등명불"
  },
  {
    "word": "일월무사조"
  },
  {
    "word": "일월문화제"
  },
  {
    "word": "일월비비추"
  },
  {
    "word": "일월성수도"
  },
  {
    "word": "일월성신도"
  },
  {
    "word": "일월오봉도"
  },
  {
    "word": "일월의정수"
  },
  {
    "word": "일월지엠엘"
  },
  {
    "word": "일월토현삼"
  },
  {
    "word": "일음일의설"
  },
  {
    "word": "일이일사태"
  },
  {
    "word": "일인용캡슐"
  },
  {
    "word": "일인칭단수"
  },
  {
    "word": "일인칭셔터"
  },
  {
    "word": "일인칭소설"
  },
  {
    "word": "일인칭시점"
  },
  {
    "word": "일인칭영화"
  },
  {
    "word": "일인칭희곡"
  },
  {
    "word": "일일난재신"
  },
  {
    "word": "일일삼삼육"
  },
  {
    "word": "일일생활권"
  },
  {
    "word": "일일여삼추"
  },
  {
    "word": "일일이제의"
  },
  {
    "word": "일자나사못"
  },
  {
    "word": "일자무소식"
  },
  {
    "word": "일자상속제"
  },
  {
    "word": "일자일석경"
  },
  {
    "word": "일자일석탑"
  },
  {
    "word": "일자장사진"
  },
  {
    "word": "일자좀나비"
  },
  {
    "word": "일전양주제"
  },
  {
    "word": "일제강점기"
  },
  {
    "word": "일종보급품"
  },
  {
    "word": "일주광행차"
  },
  {
    "word": "일주기천이"
  },
  {
    "word": "일주기활동"
  },
  {
    "word": "일주년기념"
  },
  {
    "word": "일죽중학교"
  },
  {
    "word": "일직중학교"
  },
  {
    "word": "일찍일찍이"
  },
  {
    "word": "일차감염소"
  },
  {
    "word": "일차결정화"
  },
  {
    "word": "일차계전기"
  },
  {
    "word": "일차냉각수"
  },
  {
    "word": "일차다항식"
  },
  {
    "word": "일차무지개"
  },
  {
    "word": "일차방사선"
  },
  {
    "word": "일차방정식"
  },
  {
    "word": "일차변전소"
  },
  {
    "word": "일차부등식"
  },
  {
    "word": "일차소비자"
  },
  {
    "word": "일차알코올"
  },
  {
    "word": "일차에너지"
  },
  {
    "word": "일차우주선"
  },
  {
    "word": "일차원공간"
  },
  {
    "word": "일차원자로"
  },
  {
    "word": "일차잔구멍"
  },
  {
    "word": "일차재결정"
  },
  {
    "word": "일차중성자"
  },
  {
    "word": "일채굿장단"
  },
  {
    "word": "일처다부제"
  },
  {
    "word": "일척저예망"
  },
  {
    "word": "일체경음의"
  },
  {
    "word": "일체식구조"
  },
  {
    "word": "일체식벽체"
  },
  {
    "word": "일체식층막"
  },
  {
    "word": "일체양면론"
  },
  {
    "word": "일체유위법"
  },
  {
    "word": "일추관리원"
  },
  {
    "word": "일축국백리"
  },
  {
    "word": "일축성결정"
  },
  {
    "word": "일축성관절"
  },
  {
    "word": "일출멍뭉이"
  },
  {
    "word": "일출목제공"
  },
  {
    "word": "일치규정어"
  },
  {
    "word": "일치의정리"
  },
  {
    "word": "일타스캔들"
  },
  {
    "word": "일탈하는새"
  },
  {
    "word": "일품조미료"
  },
  {
    "word": "일품짜장면"
  },
  {
    "word": "일플로탕트"
  },
  {
    "word": "일하는세포"
  },
  {
    "word": "일하는언어"
  },
  {
    "word": "일하무혜경"
  },
  {
    "word": "일학년구반"
  },
  {
    "word": "일학년일반"
  },
  {
    "word": "일허일실법"
  },
  {
    "word": "일화헛개차"
  },
  {
    "word": "일회결실성"
  },
  {
    "word": "일회박출량"
  },
  {
    "word": "일회성거래"
  },
  {
    "word": "일회호흡량"
  },
  {
    "word": "일가권속"
  },
  {
    "word": "일가문중"
  },
  {
    "word": "일가붙이"
  },
  {
    "word": "일가식솔"
  },
  {
    "word": "일가원소"
  },
  {
    "word": "일가월증"
  },
  {
    "word": "일가일신"
  },
  {
    "word": "일가친지"
  },
  {
    "word": "일가친척"
  },
  {
    "word": "일가페놀"
  },
  {
    "word": "일가함수"
  },
  {
    "word": "일각대문"
  },
  {
    "word": "일각삼례"
  },
  {
    "word": "일각선인"
  },
  {
    "word": "일각수좌"
  },
  {
    "word": "일각일각"
  },
  {
    "word": "일각일초"
  },
  {
    "word": "일각중문"
  },
  {
    "word": "일각천금"
  },
  {
    "word": "일간두옥"
  },
  {
    "word": "일간망찬"
  },
  {
    "word": "일간신문"
  },
  {
    "word": "일간조절"
  },
  {
    "word": "일간초옥"
  },
  {
    "word": "일간풍월"
  },
  {
    "word": "일개월화"
  },
  {
    "word": "일개지사"
  },
  {
    "word": "일거다득"
  },
  {
    "word": "일거두매"
  },
  {
    "word": "일거삼득"
  },
  {
    "word": "일거양득"
  },
  {
    "word": "일거양실"
  },
  {
    "word": "일거양용"
  },
  {
    "word": "일거양전"
  },
  {
    "word": "일거월저"
  },
  {
    "word": "일거이득"
  },
  {
    "word": "일거일동"
  },
  {
    "word": "일거일래"
  },
  {
    "word": "일거천리"
  },
  {
    "word": "일건기록"
  },
  {
    "word": "일건서류"
  },
  {
    "word": "일검지임"
  },
  {
    "word": "일격의검"
  },
  {
    "word": "일견여구"
  },
  {
    "word": "일결자웅"
  },
  {
    "word": "일겸사익"
  },
  {
    "word": "일경구수"
  },
  {
    "word": "일경박사"
  },
  {
    "word": "일경일희"
  },
  {
    "word": "일경지유"
  },
  {
    "word": "일경지훈"
  },
  {
    "word": "일계반급"
  },
  {
    "word": "일계일급"
  },
  {
    "word": "일고가파"
  },
  {
    "word": "일고경국"
  },
  {
    "word": "일고경성"
  },
  {
    "word": "일고삼장"
  },
  {
    "word": "일고삼척"
  },
  {
    "word": "일고일락"
  },
  {
    "word": "일고작기"
  },
  {
    "word": "일고지가"
  },
  {
    "word": "일고천금"
  },
  {
    "word": "일곡지사"
  },
  {
    "word": "일곡지인"
  },
  {
    "word": "일곱가락"
  },
  {
    "word": "일곱모꼴"
  },
  {
    "word": "일곱무날"
  },
  {
    "word": "일곱이레"
  },
  {
    "word": "일곱죄수"
  },
  {
    "word": "일곱현자"
  },
  {
    "word": "일공로동"
  },
  {
    "word": "일공이사"
  },
  {
    "word": "일공쟁이"
  },
  {
    "word": "일관삼재"
  },
  {
    "word": "일관작업"
  },
  {
    "word": "일괄감정"
  },
  {
    "word": "일괄계약"
  },
  {
    "word": "일괄처리"
  },
  {
    "word": "일괄학습"
  },
  {
    "word": "일광광산"
  },
  {
    "word": "일광기지"
  },
  {
    "word": "일광놀이"
  },
  {
    "word": "일광보살"
  },
  {
    "word": "일광삼존"
  },
  {
    "word": "일광소독"
  },
  {
    "word": "일광요법"
  },
  {
    "word": "일광욕실"
  },
  {
    "word": "일광욕장"
  },
  {
    "word": "일광절약"
  },
  {
    "word": "일광천자"
  },
  {
    "word": "일구구구"
  },
  {
    "word": "일구난설"
  },
  {
    "word": "일구양설"
  },
  {
    "word": "일구월심"
  },
  {
    "word": "일구이언"
  },
  {
    "word": "일구일갈"
  },
  {
    "word": "일구일학"
  },
  {
    "word": "일구지학"
  },
  {
    "word": "일구팔사"
  },
  {
    "word": "일국수법"
  },
  {
    "word": "일국일당"
  },
  {
    "word": "일궤십기"
  },
  {
    "word": "일귀일천"
  },
  {
    "word": "일귀하처"
  },
  {
    "word": "일규불통"
  },
  {
    "word": "일그러짐"
  },
  {
    "word": "일금일학"
  },
  {
    "word": "일급보옥"
  },
  {
    "word": "일급부하"
  },
  {
    "word": "일급비밀"
  },
  {
    "word": "일급월급"
  },
  {
    "word": "일급쟁이"
  },
  {
    "word": "일긋얄긋"
  },
  {
    "word": "일긋일긋"
  },
  {
    "word": "일기가성"
  },
  {
    "word": "일기개황"
  },
  {
    "word": "일기과정"
  },
  {
    "word": "일기관통"
  },
  {
    "word": "일기기호"
  },
  {
    "word": "일기당천"
  },
  {
    "word": "일기도형"
  },
  {
    "word": "일기문학"
  },
  {
    "word": "일기부조"
  },
  {
    "word": "일기불순"
  },
  {
    "word": "일기신호"
  },
  {
    "word": "일기실황"
  },
  {
    "word": "일기예보"
  },
  {
    "word": "일기요소"
  },
  {
    "word": "일기조직"
  },
  {
    "word": "일기지욕"
  },
  {
    "word": "일길신량"
  },
  {
    "word": "일꾼개미"
  },
  {
    "word": "일낙천금"
  },
  {
    "word": "일난풍화"
  },
  {
    "word": "일남일북"
  },
  {
    "word": "일년감빛"
  },
  {
    "word": "일년감색"
  },
  {
    "word": "일년생근"
  },
  {
    "word": "일년이면"
  },
  {
    "word": "일년전에"
  },
  {
    "word": "일년지계"
  },
  {
    "word": "일념귀명"
  },
  {
    "word": "일념발기"
  },
  {
    "word": "일념불생"
  },
  {
    "word": "일념불퇴"
  },
  {
    "word": "일념삼천"
  },
  {
    "word": "일념업성"
  },
  {
    "word": "일념왕생"
  },
  {
    "word": "일념일동"
  },
  {
    "word": "일념일불"
  },
  {
    "word": "일념창명"
  },
  {
    "word": "일념칭명"
  },
  {
    "word": "일념통천"
  },
  {
    "word": "일념포한"
  },
  {
    "word": "일념화생"
  },
  {
    "word": "일단기사"
  },
  {
    "word": "일단나와"
  },
  {
    "word": "일단일장"
  },
  {
    "word": "일단정신"
  },
  {
    "word": "일단정지"
  },
  {
    "word": "일단화기"
  },
  {
    "word": "일당독재"
  },
  {
    "word": "일당전제"
  },
  {
    "word": "일당주의"
  },
  {
    "word": "일대교잡"
  },
  {
    "word": "일대교주"
  },
  {
    "word": "일대담종"
  },
  {
    "word": "일대시교"
  },
  {
    "word": "일대잡종"
  },
  {
    "word": "일대장경"
  },
  {
    "word": "일대종신"
  },
  {
    "word": "일대호걸"
  },
  {
    "word": "일도삼례"
  },
  {
    "word": "일도양단"
  },
  {
    "word": "일도없어"
  },
  {
    "word": "일도할단"
  },
  {
    "word": "일독전쟁"
  },
  {
    "word": "일동마련"
  },
  {
    "word": "일동발사"
  },
  {
    "word": "일동일정"
  },
  {
    "word": "일득일실"
  },
  {
    "word": "일등도로"
  },
  {
    "word": "일라오이"
  },
  {
    "word": "일라이자"
  },
  {
    "word": "일라일라"
  },
  {
    "word": "일락만장"
  },
  {
    "word": "일락서산"
  },
  {
    "word": "일락천장"
  },
  {
    "word": "일락함지"
  },
  {
    "word": "일람불망"
  },
  {
    "word": "일람첩기"
  },
  {
    "word": "일람출급"
  },
  {
    "word": "일랑일랑"
  },
  {
    "word": "일랜시아"
  },
  {
    "word": "일러두기"
  },
  {
    "word": "일러스트"
  },
  {
    "word": "일러절러"
  },
  {
    "word": "일렁얄랑"
  },
  {
    "word": "일렉가드"
  },
  {
    "word": "일렉궁기"
  },
  {
    "word": "일렉러시"
  },
  {
    "word": "일렉키스"
  },
  {
    "word": "일렉키즈"
  },
  {
    "word": "일렉키퍼"
  },
  {
    "word": "일렉킹덤"
  },
  {
    "word": "일렉트렛"
  },
  {
    "word": "일렉트릭"
  },
  {
    "word": "일려단복"
  },
  {
    "word": "일련번호"
  },
  {
    "word": "일련운동"
  },
  {
    "word": "일련탁생"
  },
  {
    "word": "일렬종대"
  },
  {
    "word": "일렬횡대"
  },
  {
    "word": "일로매진"
  },
  {
    "word": "일로영일"
  },
  {
    "word": "일로일로"
  },
  {
    "word": "일로전쟁"
  },
  {
    "word": "일로평안"
  },
  {
    "word": "일로협약"
  },
  {
    "word": "일룡일사"
  },
  {
    "word": "일룡일저"
  },
  {
    "word": "일루델루"
  },
  {
    "word": "일루절루"
  },
  {
    "word": "일류신사"
  },
  {
    "word": "일류언제"
  },
  {
    "word": "일륜명월"
  },
  {
    "word": "일률천편"
  },
  {
    "word": "일리아드"
  },
  {
    "word": "일리아스"
  },
  {
    "word": "일리야스"
  },
  {
    "word": "일리오스"
  },
  {
    "word": "일리일실"
  },
  {
    "word": "일리일해"
  },
  {
    "word": "일리조약"
  },
  {
    "word": "일리피아"
  },
  {
    "word": "일립만배"
  },
  {
    "word": "일마니수"
  },
  {
    "word": "일말의색"
  },
  {
    "word": "일망무애"
  },
  {
    "word": "일망무제"
  },
  {
    "word": "일망지하"
  },
  {
    "word": "일망천리"
  },
  {
    "word": "일맥상통"
  },
  {
    "word": "일면경도"
  },
  {
    "word": "일면무대"
  },
  {
    "word": "일면부지"
  },
  {
    "word": "일면여구"
  },
  {
    "word": "일면위도"
  },
  {
    "word": "일면좌표"
  },
  {
    "word": "일면지교"
  },
  {
    "word": "일면지분"
  },
  {
    "word": "일면지영"
  },
  {
    "word": "일면천막"
  },
  {
    "word": "일면통과"
  },
  {
    "word": "일명경인"
  },
  {
    "word": "일명불시"
  },
  {
    "word": "일명일암"
  },
  {
    "word": "일모다빈"
  },
  {
    "word": "일모도궁"
  },
  {
    "word": "일모도원"
  },
  {
    "word": "일모불발"
  },
  {
    "word": "일모불백"
  },
  {
    "word": "일목대장"
  },
  {
    "word": "일목십행"
  },
  {
    "word": "일목요연"
  },
  {
    "word": "일목일초"
  },
  {
    "word": "일목장군"
  },
  {
    "word": "일목지지"
  },
  {
    "word": "일몰열매"
  },
  {
    "word": "일무가관"
  },
  {
    "word": "일무가론"
  },
  {
    "word": "일무가취"
  },
  {
    "word": "일무다빈"
  },
  {
    "word": "일무소득"
  },
  {
    "word": "일무소식"
  },
  {
    "word": "일무소장"
  },
  {
    "word": "일무소취"
  },
  {
    "word": "일무실착"
  },
  {
    "word": "일무차착"
  },
  {
    "word": "일문백홀"
  },
  {
    "word": "일문보문"
  },
  {
    "word": "일문부지"
  },
  {
    "word": "일문불통"
  },
  {
    "word": "일문일답"
  },
  {
    "word": "일문일족"
  },
  {
    "word": "일문지내"
  },
  {
    "word": "일물일가"
  },
  {
    "word": "일미동심"
  },
  {
    "word": "일바지아"
  },
  {
    "word": "일박서산"
  },
  {
    "word": "일박이일"
  },
  {
    "word": "일반감각"
  },
  {
    "word": "일반감사"
  },
  {
    "word": "일반감시"
  },
  {
    "word": "일반감정"
  },
  {
    "word": "일반강화"
  },
  {
    "word": "일반개념"
  },
  {
    "word": "일반계시"
  },
  {
    "word": "일반공연"
  },
  {
    "word": "일반과목"
  },
  {
    "word": "일반관청"
  },
  {
    "word": "일반교서"
  },
  {
    "word": "일반교양"
  },
  {
    "word": "일반교예"
  },
  {
    "word": "일반교육"
  },
  {
    "word": "일반교회"
  },
  {
    "word": "일반국도"
  },
  {
    "word": "일반균형"
  },
  {
    "word": "일반담보"
  },
  {
    "word": "일반대학"
  },
  {
    "word": "일반도야"
  },
  {
    "word": "일반명령"
  },
  {
    "word": "일반명사"
  },
  {
    "word": "일반목재"
  },
  {
    "word": "일반문법"
  },
  {
    "word": "일반배치"
  },
  {
    "word": "일반범죄"
  },
  {
    "word": "일반법학"
  },
  {
    "word": "일반부담"
  },
  {
    "word": "일반비서"
  },
  {
    "word": "일반사면"
  },
  {
    "word": "일반색명"
  },
  {
    "word": "일반세차"
  },
  {
    "word": "일반식사"
  },
  {
    "word": "일반신도"
  },
  {
    "word": "일반여권"
  },
  {
    "word": "일반예금"
  },
  {
    "word": "일반예방"
  },
  {
    "word": "일반외과"
  },
  {
    "word": "일반용어"
  },
  {
    "word": "일반은행"
  },
  {
    "word": "일반의무"
  },
  {
    "word": "일반의사"
  },
  {
    "word": "일반의지"
  },
  {
    "word": "일반이론"
  },
  {
    "word": "일반재산"
  },
  {
    "word": "일반재원"
  },
  {
    "word": "일반저당"
  },
  {
    "word": "일반전초"
  },
  {
    "word": "일반전화"
  },
  {
    "word": "일반젤리"
  },
  {
    "word": "일반조약"
  },
  {
    "word": "일반조합"
  },
  {
    "word": "일반지덕"
  },
  {
    "word": "일반지도"
  },
  {
    "word": "일반지보"
  },
  {
    "word": "일반지식"
  },
  {
    "word": "일반지원"
  },
  {
    "word": "일반지은"
  },
  {
    "word": "일반질문"
  },
  {
    "word": "일반참모"
  },
  {
    "word": "일반천금"
  },
  {
    "word": "일반축일"
  },
  {
    "word": "일반침대"
  },
  {
    "word": "일반투표"
  },
  {
    "word": "일반펫알"
  },
  {
    "word": "일반표상"
  },
  {
    "word": "일반형법"
  },
  {
    "word": "일반화학"
  },
  {
    "word": "일반회계"
  },
  {
    "word": "일반회화"
  },
  {
    "word": "일반흡수"
  },
  {
    "word": "일발불백"
  },
  {
    "word": "일발천균"
  },
  {
    "word": "일발필중"
  },
  {
    "word": "일방교통"
  },
  {
    "word": "일방부시"
  },
  {
    "word": "일방통행"
  },
  {
    "word": "일방포수"
  },
  {
    "word": "일방행위"
  },
  {
    "word": "일백수성"
  },
  {
    "word": "일버트법"
  },
  {
    "word": "일번치제"
  },
  {
    "word": "일벌백계"
  },
  {
    "word": "일벌일습"
  },
  {
    "word": "일벽만경"
  },
  {
    "word": "일별삼춘"
  },
  {
    "word": "일병태가"
  },
  {
    "word": "일보변경"
  },
  {
    "word": "일보불양"
  },
  {
    "word": "일본간장"
  },
  {
    "word": "일본뇌염"
  },
  {
    "word": "일본목련"
  },
  {
    "word": "일본반송"
  },
  {
    "word": "일본사슴"
  },
  {
    "word": "일본사초"
  },
  {
    "word": "일본서기"
  },
  {
    "word": "일본열도"
  },
  {
    "word": "일본열차"
  },
  {
    "word": "일본원정"
  },
  {
    "word": "일본침몰"
  },
  {
    "word": "일본해류"
  },
  {
    "word": "일봉서간"
  },
  {
    "word": "일부다처"
  },
  {
    "word": "일부보증"
  },
  {
    "word": "일부보험"
  },
  {
    "word": "일부상소"
  },
  {
    "word": "일부양처"
  },
  {
    "word": "일부일부"
  },
  {
    "word": "일부일앙"
  },
  {
    "word": "일부일처"
  },
  {
    "word": "일부조사"
  },
  {
    "word": "일부종목"
  },
  {
    "word": "일부종사"
  },
  {
    "word": "일부종신"
  },
  {
    "word": "일부파산"
  },
  {
    "word": "일부판결"
  },
  {
    "word": "일부판매"
  },
  {
    "word": "일분일초"
  },
  {
    "word": "일분자막"
  },
  {
    "word": "일분자층"
  },
  {
    "word": "일불가급"
  },
  {
    "word": "일불거론"
  },
  {
    "word": "일불국토"
  },
  {
    "word": "일불성도"
  },
  {
    "word": "일불세계"
  },
  {
    "word": "일불이구"
  },
  {
    "word": "일불정토"
  },
  {
    "word": "일불투족"
  },
  {
    "word": "일불현형"
  },
  {
    "word": "일비일희"
  },
  {
    "word": "일비지력"
  },
  {
    "word": "일비지로"
  },
  {
    "word": "일빈일부"
  },
  {
    "word": "일빈일소"
  },
  {
    "word": "일사무성"
  },
  {
    "word": "일사반기"
  },
  {
    "word": "일사보국"
  },
  {
    "word": "일사분구"
  },
  {
    "word": "일사분기"
  },
  {
    "word": "일사불란"
  },
  {
    "word": "일사일생"
  },
  {
    "word": "일사일언"
  },
  {
    "word": "일사일호"
  },
  {
    "word": "일사천리"
  },
  {
    "word": "일사칠궁"
  },
  {
    "word": "일사칠생"
  },
  {
    "word": "일사후퇴"
  },
  {
    "word": "일산보졸"
  },
  {
    "word": "일산보종"
  },
  {
    "word": "일산염기"
  },
  {
    "word": "일산으로"
  },
  {
    "word": "일산일수"
  },
  {
    "word": "일산화납"
  },
  {
    "word": "일산화연"
  },
  {
    "word": "일산화철"
  },
  {
    "word": "일살다생"
  },
  {
    "word": "일상군악"
  },
  {
    "word": "일상다반"
  },
  {
    "word": "일상삼매"
  },
  {
    "word": "일상생활"
  },
  {
    "word": "일상용어"
  },
  {
    "word": "일상의빛"
  },
  {
    "word": "일상일영"
  },
  {
    "word": "일상일하"
  },
  {
    "word": "일상정비"
  },
  {
    "word": "일생괴욕"
  },
  {
    "word": "일생당대"
  },
  {
    "word": "일생보처"
  },
  {
    "word": "일생불범"
  },
  {
    "word": "일생일급"
  },
  {
    "word": "일생일대"
  },
  {
    "word": "일생일사"
  },
  {
    "word": "일생일세"
  },
  {
    "word": "일생토록"
  },
  {
    "word": "일석이조"
  },
  {
    "word": "일석점호"
  },
  {
    "word": "일선지락"
  },
  {
    "word": "일설지임"
  },
  {
    "word": "일성분계"
  },
  {
    "word": "일성일쇠"
  },
  {
    "word": "일성호가"
  },
  {
    "word": "일세구천"
  },
  {
    "word": "일세일기"
  },
  {
    "word": "일세일대"
  },
  {
    "word": "일세일원"
  },
  {
    "word": "일세지웅"
  },
  {
    "word": "일소백미"
  },
  {
    "word": "일소부재"
  },
  {
    "word": "일소월원"
  },
  {
    "word": "일소천금"
  },
  {
    "word": "일수놀이"
  },
  {
    "word": "일수백확"
  },
  {
    "word": "일수불통"
  },
  {
    "word": "일수불퇴"
  },
  {
    "word": "일수양반"
  },
  {
    "word": "일수일족"
  },
  {
    "word": "일수쟁이"
  },
  {
    "word": "일수전매"
  },
  {
    "word": "일수직원"
  },
  {
    "word": "일수직자"
  },
  {
    "word": "일수직제"
  },
  {
    "word": "일수판매"
  },
  {
    "word": "일숙일반"
  },
  {
    "word": "일순천리"
  },
  {
    "word": "일슬지공"
  },
  {
    "word": "일승묘전"
  },
  {
    "word": "일승실상"
  },
  {
    "word": "일승원교"
  },
  {
    "word": "일승일부"
  },
  {
    "word": "일승일패"
  },
  {
    "word": "일승지사"
  },
  {
    "word": "일승홍선"
  },
  {
    "word": "일시경수"
  },
  {
    "word": "일시동인"
  },
  {
    "word": "일시명류"
  },
  {
    "word": "일시반때"
  },
  {
    "word": "일시생사"
  },
  {
    "word": "일시센물"
  },
  {
    "word": "일시소득"
  },
  {
    "word": "일시웅아"
  },
  {
    "word": "일시일시"
  },
  {
    "word": "일시자석"
  },
  {
    "word": "일시정지"
  },
  {
    "word": "일시지걸"
  },
  {
    "word": "일시지관"
  },
  {
    "word": "일시지권"
  },
  {
    "word": "일시풍쇄"
  },
  {
    "word": "일시해고"
  },
  {
    "word": "일식가구"
  },
  {
    "word": "일식만전"
  },
  {
    "word": "일식성염"
  },
  {
    "word": "일식요리"
  },
  {
    "word": "일신기원"
  },
  {
    "word": "일신양역"
  },
  {
    "word": "일신월성"
  },
  {
    "word": "일신월화"
  },
  {
    "word": "일신일가"
  },
  {
    "word": "일신일축"
  },
  {
    "word": "일신천금"
  },
  {
    "word": "일실동거"
  },
  {
    "word": "일실동환"
  },
  {
    "word": "일실무상"
  },
  {
    "word": "일실방식"
  },
  {
    "word": "일실원돈"
  },
  {
    "word": "일실이익"
  },
  {
    "word": "일실일득"
  },
  {
    "word": "일실주택"
  },
  {
    "word": "일심경도"
  },
  {
    "word": "일심경례"
  },
  {
    "word": "일심귀명"
  },
  {
    "word": "일심동귀"
  },
  {
    "word": "일심동력"
  },
  {
    "word": "일심동체"
  },
  {
    "word": "일심만능"
  },
  {
    "word": "일심백군"
  },
  {
    "word": "일심불란"
  },
  {
    "word": "일심삼관"
  },
  {
    "word": "일심시차"
  },
  {
    "word": "일심염불"
  },
  {
    "word": "일심운동"
  },
  {
    "word": "일심위도"
  },
  {
    "word": "일심의활"
  },
  {
    "word": "일심이문"
  },
  {
    "word": "일심전념"
  },
  {
    "word": "일심전력"
  },
  {
    "word": "일심정기"
  },
  {
    "word": "일심정념"
  },
  {
    "word": "일심정토"
  },
  {
    "word": "일심좌표"
  },
  {
    "word": "일심합장"
  },
  {
    "word": "일심협력"
  },
  {
    "word": "일아전쟁"
  },
  {
    "word": "일악대패"
  },
  {
    "word": "일안만강"
  },
  {
    "word": "일액현상"
  },
  {
    "word": "일야무간"
  },
  {
    "word": "일야부절"
  },
  {
    "word": "일야지간"
  },
  {
    "word": "일야천리"
  },
  {
    "word": "일양내복"
  },
  {
    "word": "일어탁수"
  },
  {
    "word": "일언가파"
  },
  {
    "word": "일언거사"
  },
  {
    "word": "일언단파"
  },
  {
    "word": "일언반구"
  },
  {
    "word": "일언반사"
  },
  {
    "word": "일언방은"
  },
  {
    "word": "일언일구"
  },
  {
    "word": "일언일동"
  },
  {
    "word": "일언일앙"
  },
  {
    "word": "일언일행"
  },
  {
    "word": "일언지신"
  },
  {
    "word": "일언지좌"
  },
  {
    "word": "일언지하"
  },
  {
    "word": "일언천금"
  },
  {
    "word": "일언함인"
  },
  {
    "word": "일업소감"
  },
  {
    "word": "일여관음"
  },
  {
    "word": "일여덟째"
  },
  {
    "word": "일여드레"
  },
  {
    "word": "일여일탈"
  },
  {
    "word": "일역지지"
  },
  {
    "word": "일염기산"
  },
  {
    "word": "일엽관음"
  },
  {
    "word": "일엽소선"
  },
  {
    "word": "일엽지추"
  },
  {
    "word": "일엽편주"
  },
  {
    "word": "일영곡선"
  },
  {
    "word": "일영동맹"
  },
  {
    "word": "일영삼탄"
  },
  {
    "word": "일영일락"
  },
  {
    "word": "일영일상"
  },
  {
    "word": "일오재오"
  },
  {
    "word": "일왕래과"
  },
  {
    "word": "일왕일래"
  },
  {
    "word": "일요작가"
  },
  {
    "word": "일요진단"
  },
  {
    "word": "일요토론"
  },
  {
    "word": "일요화가"
  },
  {
    "word": "일용공예"
  },
  {
    "word": "일용범백"
  },
  {
    "word": "일용상행"
  },
  {
    "word": "일용직원"
  },
  {
    "word": "일우명지"
  },
  {
    "word": "일우후지"
  },
  {
    "word": "일운도저"
  },
  {
    "word": "일웅다자"
  },
  {
    "word": "일웅일자"
  },
  {
    "word": "일원론자"
  },
  {
    "word": "일원론적"
  },
  {
    "word": "일원묘사"
  },
  {
    "word": "일원제도"
  },
  {
    "word": "일원지초"
  },
  {
    "word": "일월강습"
  },
  {
    "word": "일월광산"
  },
  {
    "word": "일월구천"
  },
  {
    "word": "일월놀음"
  },
  {
    "word": "일월삼신"
  },
  {
    "word": "일월삼주"
  },
  {
    "word": "일월설화"
  },
  {
    "word": "일월성수"
  },
  {
    "word": "일월성신"
  },
  {
    "word": "일월세차"
  },
  {
    "word": "일월여천"
  },
  {
    "word": "일월윤회"
  },
  {
    "word": "일월지명"
  },
  {
    "word": "일월지식"
  },
  {
    "word": "일유일예"
  },
  {
    "word": "일유치원"
  },
  {
    "word": "일음일식"
  },
  {
    "word": "일음일양"
  },
  {
    "word": "일음일탁"
  },
  {
    "word": "일의고행"
  },
  {
    "word": "일의대수"
  },
  {
    "word": "일의비극"
  },
  {
    "word": "일의원리"
  },
  {
    "word": "일의전심"
  },
  {
    "word": "일의직도"
  },
  {
    "word": "일의태도"
  },
  {
    "word": "일이관지"
  },
  {
    "word": "일이위상"
  },
  {
    "word": "일인당백"
  },
  {
    "word": "일인당천"
  },
  {
    "word": "일인량역"
  },
  {
    "word": "일인이역"
  },
  {
    "word": "일인일기"
  },
  {
    "word": "일인지하"
  },
  {
    "word": "일인회사"
  },
  {
    "word": "일일구천"
  },
  {
    "word": "일일년년"
  },
  {
    "word": "일일만기"
  },
  {
    "word": "일일명령"
  },
  {
    "word": "일일병력"
  },
  {
    "word": "일일사득"
  },
  {
    "word": "일일삼추"
  },
  {
    "word": "일일시시"
  },
  {
    "word": "일일일야"
  },
  {
    "word": "일일지고"
  },
  {
    "word": "일일지락"
  },
  {
    "word": "일일지아"
  },
  {
    "word": "일일지우"
  },
  {
    "word": "일일지장"
  },
  {
    "word": "일일지환"
  },
  {
    "word": "일일천리"
  },
  {
    "word": "일일천추"
  },
  {
    "word": "일일편시"
  },
  {
    "word": "일일항정"
  },
  {
    "word": "일임매매"
  },
  {
    "word": "일임식물"
  },
  {
    "word": "일자경장"
  },
  {
    "word": "일자경척"
  },
  {
    "word": "일자대형"
  },
  {
    "word": "일자리표"
  },
  {
    "word": "일자만동"
  },
  {
    "word": "일자매기"
  },
  {
    "word": "일자머리"
  },
  {
    "word": "일자무식"
  },
  {
    "word": "일자바지"
  },
  {
    "word": "일자반급"
  },
  {
    "word": "일자백금"
  },
  {
    "word": "일자백련"
  },
  {
    "word": "일자불설"
  },
  {
    "word": "일자불식"
  },
  {
    "word": "일자삼례"
  },
  {
    "word": "일자수의"
  },
  {
    "word": "일자신호"
  },
  {
    "word": "일자양의"
  },
  {
    "word": "일자오결"
  },
  {
    "word": "일자이후"
  },
  {
    "word": "일자일의"
  },
  {
    "word": "일자일점"
  },
  {
    "word": "일자일주"
  },
  {
    "word": "일자일체"
  },
  {
    "word": "일자지사"
  },
  {
    "word": "일자천금"
  },
  {
    "word": "일자첩용"
  },
  {
    "word": "일자포수"
  },
  {
    "word": "일자포폄"
  },
  {
    "word": "일잡도리"
  },
  {
    "word": "일장월취"
  },
  {
    "word": "일장일단"
  },
  {
    "word": "일장일이"
  },
  {
    "word": "일장춘몽"
  },
  {
    "word": "일장통곡"
  },
  {
    "word": "일장풍파"
  },
  {
    "word": "일재일예"
  },
  {
    "word": "일전불사"
  },
  {
    "word": "일전쌍조"
  },
  {
    "word": "일전일도"
  },
  {
    "word": "일절지사"
  },
  {
    "word": "일점쇄선"
  },
  {
    "word": "일점일획"
  },
  {
    "word": "일점혈육"
  },
  {
    "word": "일정불변"
  },
  {
    "word": "일정불역"
  },
  {
    "word": "일정시대"
  },
  {
    "word": "일정일동"
  },
  {
    "word": "일제교수"
  },
  {
    "word": "일제시대"
  },
  {
    "word": "일져므리"
  },
  {
    "word": "일졈그리"
  },
  {
    "word": "일조부귀"
  },
  {
    "word": "일조부등"
  },
  {
    "word": "일조석일"
  },
  {
    "word": "일조수아"
  },
  {
    "word": "일조시간"
  },
  {
    "word": "일조일석"
  },
  {
    "word": "일조점호"
  },
  {
    "word": "일조지분"
  },
  {
    "word": "일조지환"
  },
  {
    "word": "일조편법"
  },
  {
    "word": "일종일횡"
  },
  {
    "word": "일죄재범"
  },
  {
    "word": "일주기성"
  },
  {
    "word": "일주리듬"
  },
  {
    "word": "일주변화"
  },
  {
    "word": "일주시차"
  },
  {
    "word": "일주운동"
  },
  {
    "word": "일주일야"
  },
  {
    "word": "일주현상"
  },
  {
    "word": "일중도영"
  },
  {
    "word": "일중불결"
  },
  {
    "word": "일중행사"
  },
  {
    "word": "일즙일채"
  },
  {
    "word": "일증월가"
  },
  {
    "word": "일지반전"
  },
  {
    "word": "일지반해"
  },
  {
    "word": "일직사관"
  },
  {
    "word": "일직사령"
  },
  {
    "word": "일직사자"
  },
  {
    "word": "일진광풍"
  },
  {
    "word": "일진법계"
  },
  {
    "word": "일진불염"
  },
  {
    "word": "일진사냥"
  },
  {
    "word": "일진월보"
  },
  {
    "word": "일진음풍"
  },
  {
    "word": "일진일신"
  },
  {
    "word": "일진일퇴"
  },
  {
    "word": "일진청풍"
  },
  {
    "word": "일진흑운"
  },
  {
    "word": "일질일문"
  },
  {
    "word": "일쭉얄쭉"
  },
  {
    "word": "일쭉일쭉"
  },
  {
    "word": "일쯔가니"
  },
  {
    "word": "일찌가니"
  },
  {
    "word": "일찌감치"
  },
  {
    "word": "일찌거니"
  },
  {
    "word": "일찌겡이"
  },
  {
    "word": "일차감염"
  },
  {
    "word": "일차결합"
  },
  {
    "word": "일차관련"
  },
  {
    "word": "일차권선"
  },
  {
    "word": "일차금속"
  },
  {
    "word": "일차독립"
  },
  {
    "word": "일차떼기"
  },
  {
    "word": "일차립자"
  },
  {
    "word": "일차마디"
  },
  {
    "word": "일차박리"
  },
  {
    "word": "일차반응"
  },
  {
    "word": "일차배양"
  },
  {
    "word": "일차변환"
  },
  {
    "word": "일차비새"
  },
  {
    "word": "일차산업"
  },
  {
    "word": "일차산품"
  },
  {
    "word": "일차상품"
  },
  {
    "word": "일차생산"
  },
  {
    "word": "일차성징"
  },
  {
    "word": "일차수막"
  },
  {
    "word": "일차신호"
  },
  {
    "word": "일차욕구"
  },
  {
    "word": "일차원적"
  },
  {
    "word": "일차입자"
  },
  {
    "word": "일차전류"
  },
  {
    "word": "일차전압"
  },
  {
    "word": "일차전자"
  },
  {
    "word": "일차전지"
  },
  {
    "word": "일차제품"
  },
  {
    "word": "일차조직"
  },
  {
    "word": "일차종속"
  },
  {
    "word": "일차집단"
  },
  {
    "word": "일차처리"
  },
  {
    "word": "일차천이"
  },
  {
    "word": "일차코일"
  },
  {
    "word": "일차함수"
  },
  {
    "word": "일차회로"
  },
  {
    "word": "일창삼탄"
  },
  {
    "word": "일창일화"
  },
  {
    "word": "일채가락"
  },
  {
    "word": "일처다부"
  },
  {
    "word": "일척건곤"
  },
  {
    "word": "일척모자"
  },
  {
    "word": "일척백만"
  },
  {
    "word": "일척천금"
  },
  {
    "word": "일천만승"
  },
  {
    "word": "일천지하"
  },
  {
    "word": "일청일탁"
  },
  {
    "word": "일청전쟁"
  },
  {
    "word": "일체감정"
  },
  {
    "word": "일체개고"
  },
  {
    "word": "일체개성"
  },
  {
    "word": "일체고액"
  },
  {
    "word": "일체분신"
  },
  {
    "word": "일체유위"
  },
  {
    "word": "일체유정"
  },
  {
    "word": "일체장경"
  },
  {
    "word": "일체종지"
  },
  {
    "word": "일체주의"
  },
  {
    "word": "일체중생"
  },
  {
    "word": "일체지지"
  },
  {
    "word": "일체편고"
  },
  {
    "word": "일초광시"
  },
  {
    "word": "일초일목"
  },
  {
    "word": "일초지회"
  },
  {
    "word": "일초진자"
  },
  {
    "word": "일촉즉발"
  },
  {
    "word": "일촌간장"
  },
  {
    "word": "일촌광음"
  },
  {
    "word": "일촌단심"
  },
  {
    "word": "일촌적심"
  },
  {
    "word": "일축일신"
  },
  {
    "word": "일출사당"
  },
  {
    "word": "일출삼간"
  },
  {
    "word": "일출하늘"
  },
  {
    "word": "일취월장"
  },
  {
    "word": "일취지몽"
  },
  {
    "word": "일취천일"
  },
  {
    "word": "일측지로"
  },
  {
    "word": "일층가관"
  },
  {
    "word": "일층기관"
  },
  {
    "word": "일층회랑"
  },
  {
    "word": "일치가결"
  },
  {
    "word": "일치단결"
  },
  {
    "word": "일치협력"
  },
  {
    "word": "일칭일념"
  },
  {
    "word": "일타강사"
  },
  {
    "word": "일탁아소"
  },
  {
    "word": "일토양세"
  },
  {
    "word": "일파만파"
  },
  {
    "word": "일패도지"
  },
  {
    "word": "일편고운"
  },
  {
    "word": "일편고월"
  },
  {
    "word": "일편단심"
  },
  {
    "word": "일편도이"
  },
  {
    "word": "일편명월"
  },
  {
    "word": "일편빙심"
  },
  {
    "word": "일편지견"
  },
  {
    "word": "일편지력"
  },
  {
    "word": "일편지론"
  },
  {
    "word": "일편지언"
  },
  {
    "word": "일편지한"
  },
  {
    "word": "일편천언"
  },
  {
    "word": "일포발열"
  },
  {
    "word": "일폭십한"
  },
  {
    "word": "일품공예"
  },
  {
    "word": "일품요리"
  },
  {
    "word": "일프티라"
  },
  {
    "word": "일필구지"
  },
  {
    "word": "일필난기"
  },
  {
    "word": "일필삼례"
  },
  {
    "word": "일필휘지"
  },
  {
    "word": "일하구순"
  },
  {
    "word": "일하안거"
  },
  {
    "word": "일한사전"
  },
  {
    "word": "일한일망"
  },
  {
    "word": "일한일서"
  },
  {
    "word": "일합일리"
  },
  {
    "word": "일행삼례"
  },
  {
    "word": "일행삼매"
  },
  {
    "word": "일행천리"
  },
  {
    "word": "일향전념"
  },
  {
    "word": "일향전수"
  },
  {
    "word": "일허일실"
  },
  {
    "word": "일허일영"
  },
  {
    "word": "일현돌격"
  },
  {
    "word": "일현일몰"
  },
  {
    "word": "일호반점"
  },
  {
    "word": "일호백낙"
  },
  {
    "word": "일호재락"
  },
  {
    "word": "일호지액"
  },
  {
    "word": "일호차착"
  },
  {
    "word": "일호천금"
  },
  {
    "word": "일화배척"
  },
  {
    "word": "일화조약"
  },
  {
    "word": "일확천금"
  },
  {
    "word": "일회귀년"
  },
  {
    "word": "일회용품"
  },
  {
    "word": "일훈일유"
  },
  {
    "word": "일희일경"
  },
  {
    "word": "일희일구"
  },
  {
    "word": "일희일노"
  },
  {
    "word": "일희일비"
  },
  {
    "word": "일희일우"
  },
  {
    "word": "일가견"
  },
  {
    "word": "일가서"
  },
  {
    "word": "일가성"
  },
  {
    "word": "일가언"
  },
  {
    "word": "일가족"
  },
  {
    "word": "일각문"
  },
  {
    "word": "일각삼"
  },
  {
    "word": "일각서"
  },
  {
    "word": "일각선"
  },
  {
    "word": "일각수"
  },
  {
    "word": "일간지"
  },
  {
    "word": "일갓집"
  },
  {
    "word": "일강관"
  },
  {
    "word": "일개미"
  },
  {
    "word": "일개인"
  },
  {
    "word": "일거리"
  },
  {
    "word": "일견객"
  },
  {
    "word": "일견식"
  },
  {
    "word": "일계표"
  },
  {
    "word": "일고동"
  },
  {
    "word": "일고지"
  },
  {
    "word": "일곱물"
  },
  {
    "word": "일곱살"
  },
  {
    "word": "일곱째"
  },
  {
    "word": "일공군"
  },
  {
    "word": "일공녀"
  },
  {
    "word": "일공단"
  },
  {
    "word": "일공당"
  },
  {
    "word": "일공이"
  },
  {
    "word": "일공일"
  },
  {
    "word": "일공품"
  },
  {
    "word": "일과경"
  },
  {
    "word": "일과력"
  },
  {
    "word": "일과성"
  },
  {
    "word": "일과표"
  },
  {
    "word": "일관도"
  },
  {
    "word": "일관부"
  },
  {
    "word": "일관성"
  },
  {
    "word": "일관일"
  },
  {
    "word": "일괄적"
  },
  {
    "word": "일광경"
  },
  {
    "word": "일광단"
  },
  {
    "word": "일광등"
  },
  {
    "word": "일광역"
  },
  {
    "word": "일광욕"
  },
  {
    "word": "일광조"
  },
  {
    "word": "일광취"
  },
  {
    "word": "일괴육"
  },
  {
    "word": "일괴토"
  },
  {
    "word": "일교차"
  },
  {
    "word": "일국루"
  },
  {
    "word": "일군날"
  },
  {
    "word": "일군땅"
  },
  {
    "word": "일군빗"
  },
  {
    "word": "일군색"
  },
  {
    "word": "일근자"
  },
  {
    "word": "일급꾼"
  },
  {
    "word": "일급량"
  },
  {
    "word": "일급목"
  },
  {
    "word": "일급수"
  },
  {
    "word": "일급제"
  },
  {
    "word": "일급품"
  },
  {
    "word": "일기도"
  },
  {
    "word": "일기병"
  },
  {
    "word": "일기장"
  },
  {
    "word": "일기죽"
  },
  {
    "word": "일기책"
  },
  {
    "word": "일기청"
  },
  {
    "word": "일기체"
  },
  {
    "word": "일기초"
  },
  {
    "word": "일기축"
  },
  {
    "word": "일기회"
  },
  {
    "word": "일길간"
  },
  {
    "word": "일길찬"
  },
  {
    "word": "일깬날"
  },
  {
    "word": "일꾼날"
  },
  {
    "word": "일꿀이"
  },
  {
    "word": "일난국"
  },
  {
    "word": "일남중"
  },
  {
    "word": "일남지"
  },
  {
    "word": "일년감"
  },
  {
    "word": "일년근"
  },
  {
    "word": "일년반"
  },
  {
    "word": "일년생"
  },
  {
    "word": "일년송"
  },
  {
    "word": "일년주"
  },
  {
    "word": "일년째"
  },
  {
    "word": "일년초"
  },
  {
    "word": "일년풍"
  },
  {
    "word": "일념가"
  },
  {
    "word": "일념시"
  },
  {
    "word": "일노래"
  },
  {
    "word": "일능률"
  },
  {
    "word": "일다경"
  },
  {
    "word": "일단락"
  },
  {
    "word": "일단음"
  },
  {
    "word": "일당량"
  },
  {
    "word": "일당백"
  },
  {
    "word": "일당비"
  },
  {
    "word": "일당십"
  },
  {
    "word": "일당제"
  },
  {
    "word": "일대겁"
  },
  {
    "word": "일대교"
  },
  {
    "word": "일대기"
  },
  {
    "word": "일대다"
  },
  {
    "word": "일대백"
  },
  {
    "word": "일대사"
  },
  {
    "word": "일대식"
  },
  {
    "word": "일대일"
  },
  {
    "word": "일대전"
  },
  {
    "word": "일더위"
  },
  {
    "word": "일도류"
  },
  {
    "word": "일도조"
  },
  {
    "word": "일독회"
  },
  {
    "word": "일동무"
  },
  {
    "word": "일득록"
  },
  {
    "word": "일등객"
  },
  {
    "word": "일등국"
  },
  {
    "word": "일등미"
  },
  {
    "word": "일등병"
  },
  {
    "word": "일등성"
  },
  {
    "word": "일등실"
  },
  {
    "word": "일등지"
  },
  {
    "word": "일등친"
  },
  {
    "word": "일등칸"
  },
  {
    "word": "일등품"
  },
  {
    "word": "일라리"
  },
  {
    "word": "일라이"
  },
  {
    "word": "일람불"
  },
  {
    "word": "일람표"
  },
  {
    "word": "일랑은"
  },
  {
    "word": "일래과"
  },
  {
    "word": "일래향"
  },
  {
    "word": "일량관"
  },
  {
    "word": "일러서"
  },
  {
    "word": "일런드"
  },
  {
    "word": "일레인"
  },
  {
    "word": "일렉겔"
  },
  {
    "word": "일렌젤"
  },
  {
    "word": "일력년"
  },
  {
    "word": "일력월"
  },
  {
    "word": "일렬진"
  },
  {
    "word": "일령잠"
  },
  {
    "word": "일로린"
  },
  {
    "word": "일로스"
  },
  {
    "word": "일뢰당"
  },
  {
    "word": "일루루"
  },
  {
    "word": "일루션"
  },
  {
    "word": "일루수"
  },
  {
    "word": "일루전"
  },
  {
    "word": "일루젼"
  },
  {
    "word": "일루타"
  },
  {
    "word": "일류병"
  },
  {
    "word": "일류부"
  },
  {
    "word": "일류샤"
  },
  {
    "word": "일류신"
  },
  {
    "word": "일류언"
  },
  {
    "word": "일류제"
  },
  {
    "word": "일륙작"
  },
  {
    "word": "일륙장"
  },
  {
    "word": "일륜거"
  },
  {
    "word": "일륜월"
  },
  {
    "word": "일륜차"
  },
  {
    "word": "일륜홍"
  },
  {
    "word": "일률적"
  },
  {
    "word": "일름보"
  },
  {
    "word": "일리국"
  },
  {
    "word": "일리단"
  },
  {
    "word": "일리아"
  },
  {
    "word": "일리우"
  },
  {
    "word": "일리움"
  },
  {
    "word": "일마니"
  },
  {
    "word": "일막극"
  },
  {
    "word": "일막물"
  },
  {
    "word": "일머리"
  },
  {
    "word": "일면관"
  },
  {
    "word": "일면성"
  },
  {
    "word": "일면식"
  },
  {
    "word": "일면적"
  },
  {
    "word": "일모습"
  },
  {
    "word": "일모요"
  },
  {
    "word": "일모작"
  },
  {
    "word": "일목조"
  },
  {
    "word": "일몰시"
  },
  {
    "word": "일무리"
  },
  {
    "word": "일무위"
  },
  {
    "word": "일문전"
  },
  {
    "word": "일미선"
  },
  {
    "word": "일민가"
  },
  {
    "word": "일바람"
  },
  {
    "word": "일반각"
  },
  {
    "word": "일반객"
  },
  {
    "word": "일반격"
  },
  {
    "word": "일반급"
  },
  {
    "word": "일반도"
  },
  {
    "word": "일반론"
  },
  {
    "word": "일반미"
  },
  {
    "word": "일반법"
  },
  {
    "word": "일반석"
  },
  {
    "word": "일반성"
  },
  {
    "word": "일반세"
  },
  {
    "word": "일반수"
  },
  {
    "word": "일반식"
  },
  {
    "word": "일반어"
  },
  {
    "word": "일반용"
  },
  {
    "word": "일반은"
  },
  {
    "word": "일반인"
  },
  {
    "word": "일반자"
  },
  {
    "word": "일반적"
  },
  {
    "word": "일반직"
  },
  {
    "word": "일반차"
  },
  {
    "word": "일반항"
  },
  {
    "word": "일반해"
  },
  {
    "word": "일반화"
  },
  {
    "word": "일방보"
  },
  {
    "word": "일방적"
  },
  {
    "word": "일배성"
  },
  {
    "word": "일배수"
  },
  {
    "word": "일배주"
  },
  {
    "word": "일배체"
  },
  {
    "word": "일벌간"
  },
  {
    "word": "일벌레"
  },
  {
    "word": "일벌몬"
  },
  {
    "word": "일법계"
  },
  {
    "word": "일법랍"
  },
  {
    "word": "일법인"
  },
  {
    "word": "일변계"
  },
  {
    "word": "일변도"
  },
  {
    "word": "일변화"
  },
  {
    "word": "일병정"
  },
  {
    "word": "일보변"
  },
  {
    "word": "일보표"
  },
  {
    "word": "일복시"
  },
  {
    "word": "일본국"
  },
  {
    "word": "일본기"
  },
  {
    "word": "일본도"
  },
  {
    "word": "일본식"
  },
  {
    "word": "일본어"
  },
  {
    "word": "일본인"
  },
  {
    "word": "일본제"
  },
  {
    "word": "일본풍"
  },
  {
    "word": "일본해"
  },
  {
    "word": "일봉서"
  },
  {
    "word": "일부금"
  },
  {
    "word": "일부러"
  },
  {
    "word": "일부법"
  },
  {
    "word": "일부분"
  },
  {
    "word": "일부불"
  },
  {
    "word": "일부인"
  },
  {
    "word": "일부일"
  },
  {
    "word": "일부자"
  },
  {
    "word": "일부제"
  },
  {
    "word": "일부토"
  },
  {
    "word": "일분만"
  },
  {
    "word": "일분자"
  },
  {
    "word": "일불승"
  },
  {
    "word": "일불토"
  },
  {
    "word": "일붕사"
  },
  {
    "word": "일비국"
  },
  {
    "word": "일사계"
  },
  {
    "word": "일사랑"
  },
  {
    "word": "일사량"
  },
  {
    "word": "일사병"
  },
  {
    "word": "일사우"
  },
  {
    "word": "일사인"
  },
  {
    "word": "일산대"
  },
  {
    "word": "일산량"
  },
  {
    "word": "일산역"
  },
  {
    "word": "일삼매"
  },
  {
    "word": "일삼복"
  },
  {
    "word": "일삽시"
  },
  {
    "word": "일삽우"
  },
  {
    "word": "일상관"
  },
  {
    "word": "일상복"
  },
  {
    "word": "일상사"
  },
  {
    "word": "일상성"
  },
  {
    "word": "일상적"
  },
  {
    "word": "일상한"
  },
  {
    "word": "일상화"
  },
  {
    "word": "일생기"
  },
  {
    "word": "일선형"
  },
  {
    "word": "일성록"
  },
  {
    "word": "일성론"
  },
  {
    "word": "일성왕"
  },
  {
    "word": "일성파"
  },
  {
    "word": "일세계"
  },
  {
    "word": "일세관"
  },
  {
    "word": "일센치"
  },
  {
    "word": "일손탁"
  },
  {
    "word": "일솜씨"
  },
  {
    "word": "일수돈"
  },
  {
    "word": "일수로"
  },
  {
    "word": "일수유"
  },
  {
    "word": "일수입"
  },
  {
    "word": "일수전"
  },
  {
    "word": "일수죄"
  },
  {
    "word": "일수직"
  },
  {
    "word": "일숙박"
  },
  {
    "word": "일숙직"
  },
  {
    "word": "일순간"
  },
  {
    "word": "일숫돈"
  },
  {
    "word": "일승경"
  },
  {
    "word": "일승법"
  },
  {
    "word": "일시계"
  },
  {
    "word": "일시군"
  },
  {
    "word": "일시금"
  },
  {
    "word": "일시불"
  },
  {
    "word": "일시성"
  },
  {
    "word": "일시적"
  },
  {
    "word": "일식경"
  },
  {
    "word": "일식기"
  },
  {
    "word": "일식집"
  },
  {
    "word": "일신교"
  },
  {
    "word": "일신론"
  },
  {
    "word": "일신상"
  },
  {
    "word": "일실승"
  },
  {
    "word": "일야간"
  },
  {
    "word": "일야대"
  },
  {
    "word": "일양일"
  },
  {
    "word": "일어서"
  },
  {
    "word": "일언시"
  },
  {
    "word": "일언제"
  },
  {
    "word": "일업시"
  },
  {
    "word": "일없이"
  },
  {
    "word": "일역전"
  },
  {
    "word": "일엽주"
  },
  {
    "word": "일엽초"
  },
  {
    "word": "일영대"
  },
  {
    "word": "일영표"
  },
  {
    "word": "일오팔"
  },
  {
    "word": "일요병"
  },
  {
    "word": "일요일"
  },
  {
    "word": "일요판"
  },
  {
    "word": "일용임"
  },
  {
    "word": "일용직"
  },
  {
    "word": "일용품"
  },
  {
    "word": "일원론"
  },
  {
    "word": "일원상"
  },
  {
    "word": "일원설"
  },
  {
    "word": "일원역"
  },
  {
    "word": "일원적"
  },
  {
    "word": "일원제"
  },
  {
    "word": "일원화"
  },
  {
    "word": "일월광"
  },
  {
    "word": "일월권"
  },
  {
    "word": "일월담"
  },
  {
    "word": "일월도"
  },
  {
    "word": "일월등"
  },
  {
    "word": "일월식"
  },
  {
    "word": "일월신"
  },
  {
    "word": "일월연"
  },
  {
    "word": "일음교"
  },
  {
    "word": "일음증"
  },
  {
    "word": "일의성"
  },
  {
    "word": "일의적"
  },
  {
    "word": "일이월"
  },
  {
    "word": "일인극"
  },
  {
    "word": "일인자"
  },
  {
    "word": "일인칭"
  },
  {
    "word": "일일계"
  },
  {
    "word": "일일구"
  },
  {
    "word": "일일량"
  },
  {
    "word": "일일신"
  },
  {
    "word": "일일열"
  },
  {
    "word": "일일이"
  },
  {
    "word": "일일정"
  },
  {
    "word": "일일조"
  },
  {
    "word": "일일초"
  },
  {
    "word": "일일학"
  },
  {
    "word": "일일화"
  },
  {
    "word": "일일히"
  },
  {
    "word": "일자관"
  },
  {
    "word": "일자대"
  },
  {
    "word": "일자리"
  },
  {
    "word": "일자못"
  },
  {
    "word": "일자사"
  },
  {
    "word": "일자살"
  },
  {
    "word": "일자서"
  },
  {
    "word": "일자선"
  },
  {
    "word": "일자인"
  },
  {
    "word": "일자입"
  },
  {
    "word": "일자진"
  },
  {
    "word": "일자집"
  },
  {
    "word": "일자총"
  },
  {
    "word": "일자행"
  },
  {
    "word": "일자형"
  },
  {
    "word": "일자호"
  },
  {
    "word": "일장검"
  },
  {
    "word": "일장기"
  },
  {
    "word": "일장지"
  },
  {
    "word": "일장폭"
  },
  {
    "word": "일재간"
  },
  {
    "word": "일재미"
  },
  {
    "word": "일재복"
  },
  {
    "word": "일전기"
  },
  {
    "word": "일점홍"
  },
  {
    "word": "일정량"
  },
  {
    "word": "일정액"
  },
  {
    "word": "일정표"
  },
  {
    "word": "일정히"
  },
  {
    "word": "일제히"
  },
  {
    "word": "일졀이"
  },
  {
    "word": "일조계"
  },
  {
    "word": "일조권"
  },
  {
    "word": "일조량"
  },
  {
    "word": "일조시"
  },
  {
    "word": "일조율"
  },
  {
    "word": "일조치"
  },
  {
    "word": "일주권"
  },
  {
    "word": "일주기"
  },
  {
    "word": "일주년"
  },
  {
    "word": "일주문"
  },
  {
    "word": "일주성"
  },
  {
    "word": "일주야"
  },
  {
    "word": "일주일"
  },
  {
    "word": "일중독"
  },
  {
    "word": "일중례"
  },
  {
    "word": "일중식"
  },
  {
    "word": "일즈기"
  },
  {
    "word": "일지군"
  },
  {
    "word": "일지록"
  },
  {
    "word": "일지매"
  },
  {
    "word": "일지병"
  },
  {
    "word": "일지소"
  },
  {
    "word": "일지춘"
  },
  {
    "word": "일지필"
  },
  {
    "word": "일직병"
  },
  {
    "word": "일직선"
  },
  {
    "word": "일직성"
  },
  {
    "word": "일직원"
  },
  {
    "word": "일직자"
  },
  {
    "word": "일진법"
  },
  {
    "word": "일진작"
  },
  {
    "word": "일진풍"
  },
  {
    "word": "일진회"
  },
  {
    "word": "일쯔기"
  },
  {
    "word": "일찌기"
  },
  {
    "word": "일찍이"
  },
  {
    "word": "일차골"
  },
  {
    "word": "일차근"
  },
  {
    "word": "일차색"
  },
  {
    "word": "일차식"
  },
  {
    "word": "일차원"
  },
  {
    "word": "일차재"
  },
  {
    "word": "일차적"
  },
  {
    "word": "일차지"
  },
  {
    "word": "일차항"
  },
  {
    "word": "일찰나"
  },
  {
    "word": "일책수"
  },
  {
    "word": "일척안"
  },
  {
    "word": "일천리"
  },
  {
    "word": "일천박"
  },
  {
    "word": "일천자"
  },
  {
    "word": "일천제"
  },
  {
    "word": "일천하"
  },
  {
    "word": "일체감"
  },
  {
    "word": "일체경"
  },
  {
    "word": "일체성"
  },
  {
    "word": "일체식"
  },
  {
    "word": "일체중"
  },
  {
    "word": "일체지"
  },
  {
    "word": "일체화"
  },
  {
    "word": "일총통"
  },
  {
    "word": "일촬토"
  },
  {
    "word": "일축성"
  },
  {
    "word": "일출권"
  },
  {
    "word": "일출목"
  },
  {
    "word": "일출봉"
  },
  {
    "word": "일출시"
  },
  {
    "word": "일출종"
  },
  {
    "word": "일치법"
  },
  {
    "word": "일치성"
  },
  {
    "word": "일치점"
  },
  {
    "word": "일탄지"
  },
  {
    "word": "일터로"
  },
  {
    "word": "일테면"
  },
  {
    "word": "일토시"
  },
  {
    "word": "일편심"
  },
  {
    "word": "일편주"
  },
  {
    "word": "일평균"
  },
  {
    "word": "일평생"
  },
  {
    "word": "일포제"
  },
  {
    "word": "일표음"
  },
  {
    "word": "일푼전"
  },
  {
    "word": "일품경"
  },
  {
    "word": "일품군"
  },
  {
    "word": "일필경"
  },
  {
    "word": "일필서"
  },
  {
    "word": "일필화"
  },
  {
    "word": "일한국"
  },
  {
    "word": "일할표"
  },
  {
    "word": "일함수"
  },
  {
    "word": "일핵성"
  },
  {
    "word": "일핵체"
  },
  {
    "word": "일행서"
  },
  {
    "word": "일향기"
  },
  {
    "word": "일현금"
  },
  {
    "word": "일현령"
  },
  {
    "word": "일호령"
  },
  {
    "word": "일호선"
  },
  {
    "word": "일호천"
  },
  {
    "word": "일홀도"
  },
  {
    "word": "일화국"
  },
  {
    "word": "일화기"
  },
  {
    "word": "일화선"
  },
  {
    "word": "일화성"
  },
  {
    "word": "일화잠"
  },
  {
    "word": "일화집"
  },
  {
    "word": "일환성"
  },
  {
    "word": "일환책"
  },
  {
    "word": "일회갑"
  },
  {
    "word": "일회기"
  },
  {
    "word": "일회성"
  },
  {
    "word": "일회용"
  },
  {
    "word": "일회전"
  },
  {
    "word": "일회태"
  },
  {
    "word": "일가"
  },
  {
    "word": "일각"
  },
  {
    "word": "일간"
  },
  {
    "word": "일갈"
  },
  {
    "word": "일감"
  },
  {
    "word": "일강"
  },
  {
    "word": "일개"
  },
  {
    "word": "일거"
  },
  {
    "word": "일건"
  },
  {
    "word": "일격"
  },
  {
    "word": "일견"
  },
  {
    "word": "일결"
  },
  {
    "word": "일겸"
  },
  {
    "word": "일경"
  },
  {
    "word": "일계"
  },
  {
    "word": "일고"
  },
  {
    "word": "일곡"
  },
  {
    "word": "일곱"
  },
  {
    "word": "일공"
  },
  {
    "word": "일과"
  },
  {
    "word": "일곽"
  },
  {
    "word": "일관"
  },
  {
    "word": "일괄"
  },
  {
    "word": "일광"
  },
  {
    "word": "일교"
  },
  {
    "word": "일구"
  },
  {
    "word": "일국"
  },
  {
    "word": "일군"
  },
  {
    "word": "일궤"
  },
  {
    "word": "일규"
  },
  {
    "word": "일극"
  },
  {
    "word": "일근"
  },
  {
    "word": "일금"
  },
  {
    "word": "일급"
  },
  {
    "word": "일긋"
  },
  {
    "word": "일긔"
  },
  {
    "word": "일기"
  },
  {
    "word": "일긴"
  },
  {
    "word": "일길"
  },
  {
    "word": "일껀"
  },
  {
    "word": "일껏"
  },
  {
    "word": "일꾼"
  },
  {
    "word": "일끝"
  },
  {
    "word": "일낙"
  },
  {
    "word": "일남"
  },
  {
    "word": "일내"
  },
  {
    "word": "일네"
  },
  {
    "word": "일녀"
  },
  {
    "word": "일념"
  },
  {
    "word": "일능"
  },
  {
    "word": "일다"
  },
  {
    "word": "일단"
  },
  {
    "word": "일당"
  },
  {
    "word": "일대"
  },
  {
    "word": "일덕"
  },
  {
    "word": "일뎡"
  },
  {
    "word": "일도"
  },
  {
    "word": "일독"
  },
  {
    "word": "일동"
  },
  {
    "word": "일등"
  },
  {
    "word": "일라"
  },
  {
    "word": "일락"
  },
  {
    "word": "일람"
  },
  {
    "word": "일랍"
  },
  {
    "word": "일랑"
  },
  {
    "word": "일래"
  },
  {
    "word": "일레"
  },
  {
    "word": "일력"
  },
  {
    "word": "일련"
  },
  {
    "word": "일렬"
  },
  {
    "word": "일령"
  },
  {
    "word": "일례"
  },
  {
    "word": "일로"
  },
  {
    "word": "일록"
  },
  {
    "word": "일롱"
  },
  {
    "word": "일루"
  },
  {
    "word": "일룸"
  },
  {
    "word": "일류"
  },
  {
    "word": "일륜"
  },
  {
    "word": "일률"
  },
  {
    "word": "일륭"
  },
  {
    "word": "일리"
  },
  {
    "word": "일린"
  },
  {
    "word": "일마"
  },
  {
    "word": "일만"
  },
  {
    "word": "일말"
  },
  {
    "word": "일망"
  },
  {
    "word": "일맥"
  },
  {
    "word": "일면"
  },
  {
    "word": "일명"
  },
  {
    "word": "일모"
  },
  {
    "word": "일목"
  },
  {
    "word": "일몫"
  },
  {
    "word": "일몰"
  },
  {
    "word": "일몽"
  },
  {
    "word": "일무"
  },
  {
    "word": "일문"
  },
  {
    "word": "일물"
  },
  {
    "word": "일미"
  },
  {
    "word": "일민"
  },
  {
    "word": "일밀"
  },
  {
    "word": "일박"
  },
  {
    "word": "일반"
  },
  {
    "word": "일발"
  },
  {
    "word": "일밥"
  },
  {
    "word": "일방"
  },
  {
    "word": "일밭"
  },
  {
    "word": "일백"
  },
  {
    "word": "일벌"
  },
  {
    "word": "일벗"
  },
  {
    "word": "일변"
  },
  {
    "word": "일별"
  },
  {
    "word": "일병"
  },
  {
    "word": "일보"
  },
  {
    "word": "일복"
  },
  {
    "word": "일본"
  },
  {
    "word": "일봉"
  },
  {
    "word": "일부"
  },
  {
    "word": "일분"
  },
  {
    "word": "일불"
  },
  {
    "word": "일비"
  },
  {
    "word": "일사"
  },
  {
    "word": "일삭"
  },
  {
    "word": "일삯"
  },
  {
    "word": "일산"
  },
  {
    "word": "일상"
  },
  {
    "word": "일새"
  },
  {
    "word": "일색"
  },
  {
    "word": "일생"
  },
  {
    "word": "일서"
  },
  {
    "word": "일석"
  },
  {
    "word": "일선"
  },
  {
    "word": "일설"
  },
  {
    "word": "일성"
  },
  {
    "word": "일세"
  },
  {
    "word": "일소"
  },
  {
    "word": "일속"
  },
  {
    "word": "일손"
  },
  {
    "word": "일수"
  },
  {
    "word": "일숙"
  },
  {
    "word": "일순"
  },
  {
    "word": "일습"
  },
  {
    "word": "일승"
  },
  {
    "word": "일시"
  },
  {
    "word": "일식"
  },
  {
    "word": "일신"
  },
  {
    "word": "일실"
  },
  {
    "word": "일심"
  },
  {
    "word": "일싸"
  },
  {
    "word": "일쑤"
  },
  {
    "word": "일악"
  },
  {
    "word": "일안"
  },
  {
    "word": "일애"
  },
  {
    "word": "일액"
  },
  {
    "word": "일야"
  },
  {
    "word": "일약"
  },
  {
    "word": "일양"
  },
  {
    "word": "일어"
  },
  {
    "word": "일언"
  },
  {
    "word": "일업"
  },
  {
    "word": "일여"
  },
  {
    "word": "일역"
  },
  {
    "word": "일연"
  },
  {
    "word": "일엽"
  },
  {
    "word": "일영"
  },
  {
    "word": "일예"
  },
  {
    "word": "일오"
  },
  {
    "word": "일옷"
  },
  {
    "word": "일와"
  },
  {
    "word": "일왈"
  },
  {
    "word": "일요"
  },
  {
    "word": "일욕"
  },
  {
    "word": "일용"
  },
  {
    "word": "일우"
  },
  {
    "word": "일운"
  },
  {
    "word": "일원"
  },
  {
    "word": "일월"
  },
  {
    "word": "일위"
  },
  {
    "word": "일유"
  },
  {
    "word": "일은"
  },
  {
    "word": "일음"
  },
  {
    "word": "일읍"
  },
  {
    "word": "일의"
  },
  {
    "word": "일이"
  },
  {
    "word": "일익"
  },
  {
    "word": "일인"
  },
  {
    "word": "일일"
  },
  {
    "word": "일임"
  },
  {
    "word": "일입"
  },
  {
    "word": "일자"
  },
  {
    "word": "일작"
  },
  {
    "word": "일잠"
  },
  {
    "word": "일장"
  },
  {
    "word": "일재"
  },
  {
    "word": "일적"
  },
  {
    "word": "일전"
  },
  {
    "word": "일절"
  },
  {
    "word": "일점"
  },
  {
    "word": "일정"
  },
  {
    "word": "일제"
  },
  {
    "word": "일졀"
  },
  {
    "word": "일조"
  },
  {
    "word": "일족"
  },
  {
    "word": "일종"
  },
  {
    "word": "일좌"
  },
  {
    "word": "일죄"
  },
  {
    "word": "일주"
  },
  {
    "word": "일준"
  },
  {
    "word": "일중"
  },
  {
    "word": "일즉"
  },
  {
    "word": "일즙"
  },
  {
    "word": "일즛"
  },
  {
    "word": "일증"
  },
  {
    "word": "일지"
  },
  {
    "word": "일직"
  },
  {
    "word": "일진"
  },
  {
    "word": "일질"
  },
  {
    "word": "일집"
  },
  {
    "word": "일쭉"
  },
  {
    "word": "일찍"
  },
  {
    "word": "일차"
  },
  {
    "word": "일착"
  },
  {
    "word": "일참"
  },
  {
    "word": "일채"
  },
  {
    "word": "일책"
  },
  {
    "word": "일처"
  },
  {
    "word": "일척"
  },
  {
    "word": "일천"
  },
  {
    "word": "일철"
  },
  {
    "word": "일청"
  },
  {
    "word": "일체"
  },
  {
    "word": "일초"
  },
  {
    "word": "일촌"
  },
  {
    "word": "일총"
  },
  {
    "word": "일촬"
  },
  {
    "word": "일축"
  },
  {
    "word": "일출"
  },
  {
    "word": "일취"
  },
  {
    "word": "일층"
  },
  {
    "word": "일치"
  },
  {
    "word": "일침"
  },
  {
    "word": "일칸"
  },
  {
    "word": "일쿰"
  },
  {
    "word": "일탄"
  },
  {
    "word": "일탈"
  },
  {
    "word": "일탕"
  },
  {
    "word": "일태"
  },
  {
    "word": "일터"
  },
  {
    "word": "일통"
  },
  {
    "word": "일퇴"
  },
  {
    "word": "일파"
  },
  {
    "word": "일판"
  },
  {
    "word": "일패"
  },
  {
    "word": "일편"
  },
  {
    "word": "일폭"
  },
  {
    "word": "일표"
  },
  {
    "word": "일품"
  },
  {
    "word": "일풍"
  },
  {
    "word": "일필"
  },
  {
    "word": "일하"
  },
  {
    "word": "일학"
  },
  {
    "word": "일한"
  },
  {
    "word": "일할"
  },
  {
    "word": "일합"
  },
  {
    "word": "일해"
  },
  {
    "word": "일행"
  },
  {
    "word": "일향"
  },
  {
    "word": "일헌"
  },
  {
    "word": "일헤"
  },
  {
    "word": "일현"
  },
  {
    "word": "일혈"
  },
  {
    "word": "일호"
  },
  {
    "word": "일화"
  },
  {
    "word": "일확"
  },
  {
    "word": "일환"
  },
  {
    "word": "일활"
  },
  {
    "word": "일회"
  },
  {
    "word": "일후"
  },
  {
    "word": "일훈"
  },
  {
    "word": "일훔"
  },
  {
    "word": "일흔"
  },
  {
    "word": "일흥"
  },
  {
    "word": "일희"
  },
  {
    "word": "일히"
  },
  {
    "word": "일힘"
  },
  {
    "word": "일"
  }
]